Workbook
Name IQ_CH: 110000
Name IQ_CQ: 5000
Name IQ_CY: 10000
Name IQ_DAILY: 500000
Name IQ_FH: 100000
Name IQ_FQ: 500
Name IQ_FY: 1000
Name IQ_LTM: 2000
Name IQ_MONTH: 15000
Name IQ_NTM: 6000
Name IQ_WEEK: 50000
Name IQ_YTD: 3000

Sheet Firms
A1: Firm Name | B1: Type | C1: State | D1: City | E1: Website | F1: US Investments | G1: Revenue Min ($M) | H1: Revenue Max ($M) | I1: EBITDA Min ($M) | J1: EBITDA Max ($M) | K1: EV Min ($M) | L1: EV Max ($M) | M1: Check Min ($M) | N1: Check Max ($M) | O1: Deal Types | P1: Sector Tier 1 | Q1: Sector Tier 2 | R1: Sector Tier 3 | S1: Exclusions | T1: AUM ($M) | U1: Activity | V1: Last Deal | W1: Fund Name | X1: Confidence | Y1: Needs Review | Z1: Last Checked | AA1: Status | AB1: Notes
A2: 26North Partners LP | B2: PE | E2: https://www.26n.com | F2: primarily | O2: Buyout | P2: Generalist, Technology | T2: 5900.0 | U2: Active | V2: 2026-03-31 | W2: 26North Inaugural Private Equity Fund | X2: Medium | Y2: No | Z2: 2026-06-07 | AA2: complete | AB2: Seeded from CapIQ export. Numeric fields are regex first-pass — crawler will confirm. capiq_description preserved for AI extraction fallback. | [extractor] 26North Partners LP is a next-generation alternatives platform founded by Josh Harris, with strategies spanning private equity (buyouts), direct lending, investment grade alpha (credit), and insurance. Raised $5.9B for inaugural PE fund in April 2026, surpassing $4B target (Bloomberg headline references $6B). Most recent deal: acquisition of Intermedia (cloud communications firm), announced March 31, 2026. HQ city/state not confirmed from source pages. Sector focus is generalist with a notable technology deal (Intermedia). Press release PDF found: https://www.26n.com/~/media/Files/T/twentysix-north/Universal/news/26-north-raises-5-9-billion-for-inaugural-private-equity-fund-surpassing-4-billion-target.pdf — not parsed. Deal PDF found: https://www.26n.com/~/media/Files/T/twentysix-north/Universal/news/26-north-to-acquire-leading-cloud-communications-firm-intermedia.pdf — not parsed. No explicit investment criteria (revenue, EBITDA, check size, EV thresholds) found on site. | AC2: =COUNTIF(Sheet1!$A$1:$A$50,Firms!A2) -> 0
A3: 4x4 Capital, LLC | B3: Other | E3: https://4x4capital.com | P3: Consumer | U3: Active | X3: Low | Y3: Yes | Z3: 2026-06-07 | AA3: complete | AB3: Seeded from CapIQ export. Numeric fields are regex first-pass — crawler will confirm. capiq_description preserved for AI extraction fallback. | [extractor] Strategy page provided contains only navigation menu and header HTML; no substantive investment criteria, fund details, deal types, sectors, or financial parameters are visible in the supplied content. Full page content appears truncated. Requires review of complete website pages (About, Portfolio, Team, News sections) or direct contact to extract investment criteria. | AC3: =COUNTIF(Sheet1!$A$1:$A$50,Firms!A3) -> 0
A4: A&M Capital Advisors, LP | B4: PE | C4: CT | D4: Greenwich | E4: https://www.a-mcapital.com | F4: primarily | I4: 15.0 | J4: 100.0 | K4: 75.0 | L4: 750.0 | M4: 25.0 | N4: 200.0 | O4: Buyout, Recap, Other | P4: Business Services, Healthcare, Industrials | Q4: Financial Services, Consumer, Government Services | T4: 5900.0 | U4: Active | X4: High | Y4: No | Z4: 2026-06-07 | AA4: complete | AB4: Seeded from CapIQ export. Numeric fields are regex first-pass — crawler will confirm. capiq_description preserved for AI extraction fallback. | [extractor] Multi-strategy PE firm with 4 distinct investment strategies (AMCP, AMCS, AMCE, AMCSI). Data extracted from primary investment criteria sections. AMCP flagship strategy: $3.0B AUM, $60-200M check size, $150-750M target EV, $20-100M EBITDA. AMCS secondaries: $25-75M initial checks, $100-500M EV, $15M+ underlying EBITDA. AMCE (Europe): €650M AUM (~$710M USD). AMCSI: $10-50M checks, $100M+ EV, $20M+ EBITDA. Total firm AUM stated as $5.9B. Transaction types include founder transitions, build-ups, corporate divestitures, public-to-privates, and special situations. Active investor with 170+ companies invested across 24 platforms since inception. | AC4: =COUNTIF(Sheet1!$A$1:$A$50,Firms!A4) -> 1 | AD4: =SUBSTITUTE(AB4,"Seeded from CapIQ export. Numeric fields are regex first-pass — c","C") -> Crawler will confirm. capiq_description preserved for AI extraction fallback. | [extractor] Multi-strategy PE firm with 4 distinct investment strategies (AMCP, AMCS, AMCE, AMCSI). Data extracted from primary investment criteria sections. AMCP flagship strategy: $3.0B AUM, $60-200M check size, $150-750M target EV, $20-100M EBITDA. AMCS secondaries: $25-75M initial checks, $100-500M EV, $15M+ underlying EBITDA. AMCE (Europe): €650M AUM (~$710M USD). AMCSI: $10-50M checks, $100M+ EV, $20M+ EBITDA. Total firm AUM stated as $5.9B. Transaction types include founder transitions, build-ups, corporate divestitures, public-to-privates, and special situations. Active investor with 170+ companies invested across 24 platforms since inception.
A5: AAVIN Private Equity Advisors | B5: PE | C5: IA | D5: Cedar Rapids | E5: https://www.aavin.com | F5: primarily | G5: 5.0 | H5: 50.0 | I5: 1.5 | J5: 5.0 | O5: Buyout, Recap | P5: Generalist | T5: 330.0 | U5: Active | V5: 2022 | X5: High | Y5: No | Z5: 2026-06-07 | AA5: complete | AB5: Seeded from CapIQ export. Numeric fields are regex first-pass — crawler will confirm. capiq_description preserved for AI extraction fallback. | [extractor] Explicit investment criteria found on website. Founded 1999, managing lower-middle market buyouts and recaps of founder/family-owned businesses. 50+ years of legacy (predecessor organizations). 300+ completed investments. Focus on underserved geographies in Middle America with particular emphasis on succession planning. SBIC licensee. No specific fund vintage or AUM disclosed. Portfolio and recent exits sections referenced but not detailed in source. | AC5: =COUNTIF(Sheet1!$A$1:$A$50,Firms!A5) -> 0
A6: AE Industrial Partners, LP | B6: PE | C6: FL | D6: Boca Raton | E6: https://www.aeroequity.com | F6: true | O6: Buyout, Minority | P6: Industrials, Technology | U6: Active | V6: 2025-06-01 | X6: Medium | Y6: No | Z6: 2026-06-07 | AA6: complete | AB6: Seeded from CapIQ export. Numeric fields are regex first-pass — crawler will confirm. capiq_description preserved for AI extraction fallback. | [extractor] AE Industrial Partners is a PE firm focused on aerospace, national security, and industrial services. Founded 2015. 30+ platform companies and 80+ minority/add-on investments completed. Two PDFs available but not parsed: 2025 Year In Review (https://www.aeroequity.com/wp-content/uploads/AE-Industrial-Partners-2025-Year-In-Review.pdf) and Fact Sheet April 2026 (https://www.aeroequity.com/wp-content/uploads/AE-Industrial-Fact-Sheet-April-2026.pdf). Also operates AE Ventures (early-stage tech) and AEI Aerospace Leasing. Additional office in Washington, D.C. | AC6: =COUNTIF(Sheet1!$A$1:$A$50,Firms!A6) -> 1 | AD6: =SUBSTITUTE(AB6,"Seeded from CapIQ export. Numeric fields are regex first-pass — c","C") -> Crawler will confirm. capiq_description preserved for AI extraction fallback. | [extractor] AE Industrial Partners is a PE firm focused on aerospace, national security, and industrial services. Founded 2015. 30+ platform companies and 80+ minority/add-on investments completed. Two PDFs available but not parsed: 2025 Year In Review (https://www.aeroequity.com/wp-content/uploads/AE-Industrial-Partners-2025-Year-In-Review.pdf) and Fact Sheet April 2026 (https://www.aeroequity.com/wp-content/uploads/AE-Industrial-Fact-Sheet-April-2026.pdf). Also operates AE Ventures (early-stage tech) and AEI Aerospace Leasing. Additional office in Washington, D.C.
A7: AEA Investors LP | B7: PE | E7: https://www.aeainvestors.com | O7: Buyout | P7: Business Services, Consumer, Industrials | T7: 18000.0 | U7: Active | X7: Medium | Y7: No | Z7: 2026-06-07 | AA7: complete | AB7: Seeded from CapIQ export. Numeric fields are regex first-pass — crawler will confirm. capiq_description preserved for AI extraction fallback. | [extractor] AEA Investors LP is a multi-platform PE firm with four investment groups: Middle Market Private Equity, Enterprise, Elevate, and Private Debt. Pages provided show portfolio structure but no actual portfolio companies displayed (filter results empty). Firm focuses on backing founders/management teams and transforming/accelerating growth. Elevate specifically targets professional services with technology/AI. No HQ location, fund details, AUM, check sizes, or specific deal criteria found in provided content. Needs additional sources for complete criteria extraction. | AC7: =COUNTIF(Sheet1!$A$1:$A$50,Firms!A7) -> 0
A8: AFM Capital Partners, Inc. | B8: Other | E8: https://www.afmcap.com | P8: Industrials, Healthcare, Consumer | U8: Active | X8: Low | Y8: Yes | Z8: 2026-06-07 | AA8: complete | AB8: Seeded from CapIQ export. Numeric fields are regex first-pass — crawler will confirm. capiq_description preserved for AI extraction fallback. | [extractor] Portfolio page accessed but contains only HTML/CSS boilerplate and schema markup. No investment criteria, fund details, or portfolio company information extracted. Page shows company name 'AFM Capital Partners' and tagline 'Building Great Companies for Long-term Success'. One portfolio company image reference: Incodema3D. Insufficient data to populate investment criteria. Recommend review of main website pages or criteria document. | AC8: =COUNTIF(Sheet1!$A$1:$A$50,Firms!A8) -> 0
A9: Abacus Global Management, Inc. (NYSE:ABX) | B9: Other | E9: https://abacusgm.com | F9: primarily | O9: Other | P9: Financial Services | T9: 3000.0 | X9: Medium | Y9: No | Z9: 2026-06-07 | AA9: complete | AB9: Seeded from CapIQ export. Numeric fields are regex first-pass — crawler will confirm. capiq_description preserved for AI extraction fallback. | [extractor] Abacus Global Management (NYSE: ABX) is a publicly traded company, not a traditional PE/VC firm. Primary business is acquiring and managing life insurance policies as an alternative asset class via subsidiary Abacus Life Solutions. AUM of ~$3 billion stated on site. Operating in 49 states. Founded 2004. Over $10B in face value of policies purchased. 78 institutional investor partners. HQ city/state not confirmed from content provided. Firm type is closest to 'Other' as it is a publicly listed alternative asset manager focused on life settlements. Deal types do not map cleanly to standard PE/VC categories. Needs review due to non-standard firm classification and ambiguous investment criteria. | AC9: =COUNTIF(Sheet1!$A$1:$A$50,Firms!A9) -> 0
A10: Accel-KKR LLC | B10: PE | C10: CA | D10: Menlo Park | E10: https://www.accel-kkr.com | F10: true | H10: 200.0 | O10: Buyout, Growth Equity, Other | P10: Technology | T10: 21000.0 | U10: Active | X10: Medium | Y10: No | Z10: 2026-06-07 | AA10: complete | AB10: Seeded from CapIQ export. Numeric fields are regex first-pass — crawler will confirm. capiq_description preserved for AI extraction fallback. | [extractor] Accel-KKR is a PE specialist in mid-market software and tech-enabled services. Explicit investment criteria: company revenue up to $200M+, founder-owned or closely-held private companies, structures include buyouts, minority growth capital, corporate carveouts, take-privates, credit investments, and secondaries. Firm has made 500+ software investments over 25 years. Multiple office locations: Menlo Park (HQ), Atlanta, Chicago, London. No specific fund details, AUM, or minimum check size disclosed on the provided page. | AC10: =COUNTIF(Sheet1!$A$1:$A$50,Firms!A10) -> 0
A11: Acorn Growth Companies, LLC | B11: PE | E11: https://www.acorncapitalmanagement.com | F11: true | G11: 30.0 | H11: 200.0 | O11: Buyout | P11: Industrials, Business Services | T11: 893.18 | U11: Active | X11: High | Y11: No | Z11: 2026-06-07 | AA11: complete | AB11: Seeded from CapIQ export. Numeric fields are regex first-pass — crawler will confirm. capiq_description preserved for AI extraction fallback. | [extractor] Investment criteria page describes $30-200M range, strong financial performers, industry-focused opportunities in aerospace, defense, intelligence, and space markets. Firm appears to be Acorn Capital Management (not LLC). HQ location not provided on page. Last modified June 2024 indicates active status. | AC11: =COUNTIF(Sheet1!$A$1:$A$50,Firms!A11) -> 0
A12: Advent International, L.P. | B12: PE | E12: https://www.adventinternational.com | P12: Financial Services, Energy, Industrials | U12: Active | X12: Low | Y12: Yes | Z12: 2026-06-07 | AA12: complete | AB12: Seeded from CapIQ export. Numeric fields are regex first-pass — crawler will confirm. capiq_description preserved for AI extraction fallback. | [extractor] Page is investment strategy landing page with minimal extractable criteria. Schema markup confirms Advent International is a PE firm with five core sectors mentioned but sector names not visible in provided content. No financial metrics, deal sizes, fund details, or HQ location found. Full strategy details likely behind accordions/expandable sections not fully rendered in source. Needs review of complete page HTML or additional sources. | AC12: =COUNTIF(Sheet1!$A$1:$A$50,Firms!A12) -> 0
A13: Afinitas, Inc. | B13: Other | C13: MO | D13: St. Louis | E13: https://www.afinitas.com | X13: Low | Y13: Yes | Z13: 2026-06-07 | AA13: complete | AB13: Seeded from CapIQ export. Numeric fields are regex first-pass — crawler will confirm. capiq_description preserved for AI extraction fallback. | [extractor] Afinitas, Inc. is a manufacturer and distributor of precast concrete equipment, forming systems, and concrete accessories—not a PE/VC firm. The source page describes a commercial equipment company, not an investment fund. No investment criteria, deal types, fund information, or portfolio data present. This appears to be a data extraction error or misfiled company. | AC13: =COUNTIF(Sheet1!$A$1:$A$50,Firms!A13) -> 0
A14: Agellus Capital, LLC | B14: PE | E14: https://www.agellus.com | F14: true | I14: 2.0 | J14: 25.0 | O14: Buyout | P14: Business Services, Consumer, Industrials | S14: discretionaryconsumerservices | T14: 400.0 | U14: Active | V14: 2026-03-01 | W14: Fund I | X14: High | Y14: No | Z14: 2026-06-07 | AA14: complete | AB14: Seeded from CapIQ export. Numeric fields are regex first-pass — crawler will confirm. capiq_description preserved for AI extraction fallback. | [extractor] PE firm focused on essential, non-discretionary services. Platform target: $2-25M EBITDA; add-ons any size. Buy-and-build strategy with focus on fragmented markets. Three key verticals: B2B Services, Non-Discretionary Consumer Services, Supply Chain & Infrastructure. Recent investments: Bluejack (Dec 2024), CompassMSP (Sept 2024), HighGrove (Nov 2025), Titan Restoration (Mar 2026). HQ location not explicitly stated on pages provided. Tearsheet PDF available: https://www.agellus.com/documents/FG/agellus/about/652199_Agellus_Tearsheet_-_Feb_2026_1.pdf | AC14: =COUNTIF(Sheet1!$A$1:$A$50,Firms!A14) -> 1 | AD14: =SUBSTITUTE(AB14,"Seeded from CapIQ export. Numeric fields are regex first-pass — c","C") -> Crawler will confirm. capiq_description preserved for AI extraction fallback. | [extractor] PE firm focused on essential, non-discretionary services. Platform target: $2-25M EBITDA; add-ons any size. Buy-and-build strategy with focus on fragmented markets. Three key verticals: B2B Services, Non-Discretionary Consumer Services, Supply Chain & Infrastructure. Recent investments: Bluejack (Dec 2024), CompassMSP (Sept 2024), HighGrove (Nov 2025), Titan Restoration (Mar 2026). HQ location not explicitly stated on pages provided. Tearsheet PDF available: https://www.agellus.com/documents/FG/agellus/about/652199_Agellus_Tearsheet_-_Feb_2026_1.pdf
A15: Align Capital Partners, LP | B15: PE | C15: TX | D15: Dallas | E15: https://www.aligncp.com | F15: primarily | I15: 3.0 | J15: 15.0 | L15: 150.0 | M15: 20.0 | N15: 60.0 | O15: Buyout | P15: Technology, Business Services, Industrials | T15: 2100.0 | U15: Active | V15: 2026-05-28 | X15: High | Y15: No | Z15: 2026-06-07 | AA15: complete | AB15: Seeded from CapIQ export. Numeric fields are regex first-pass — crawler will confirm. capiq_description preserved for AI extraction fallback. | [extractor] Control-focused PE firm with offices in Cleveland and Dallas. Explicitly targets lower-middle market companies with 3-15mm EBITDA (or >5mm ARR for software). Check sizes 20-60mm hold value. Core criteria: actionable organic growth, recurring revenue, niche leadership, 30%+ gross margins, 15%+ EBITDA margins. North America focus (primarily US). Recent deals through May 2026. PDF overview available at https://aligncp.com/wp-content/uploads/ACP-Firm-Overview.pdf | AC15: =COUNTIF(Sheet1!$A$1:$A$50,Firms!A15) -> 1 | AD15: =SUBSTITUTE(AB15,"Seeded from CapIQ export. Numeric fields are regex first-pass — c","C") -> Crawler will confirm. capiq_description preserved for AI extraction fallback. | [extractor] Control-focused PE firm with offices in Cleveland and Dallas. Explicitly targets lower-middle market companies with 3-15mm EBITDA (or >5mm ARR for software). Check sizes 20-60mm hold value. Core criteria: actionable organic growth, recurring revenue, niche leadership, 30%+ gross margins, 15%+ EBITDA margins. North America focus (primarily US). Recent deals through May 2026. PDF overview available at https://aligncp.com/wp-content/uploads/ACP-Firm-Overview.pdf
A16: Almanac Realty Investors, LLC | B16: PE | E16: https://www.almanacrealty.com | F16: primarily | O16: Growth Equity, Minority | P16: Real Estate, Infrastructure | T16: 6000.0 | U16: Active | W16: Almanac Realty | X16: Medium | Y16: No | Z16: 2026-06-07 | AA16: complete | AB16: Seeded from CapIQ export. Numeric fields are regex first-pass — crawler will confirm. capiq_description preserved for AI extraction fallback. | [extractor] Almanac Realty is a real estate-focused investment platform under Neuberger Berman with $6B+ AUM. Two primary strategies: (1) Entity Level—growth capital investments in mid-sized real estate owners/operators; (2) GP Stakes—minority equity in real estate investment managers. Also manages Real Estate Secondaries ($25B commitments) and Real Estate Private Credit ($37.6B+ invested). 59 transactions since inception, 26 avg years IC experience. Operating since 1996. North American focus. HQ location not explicitly stated on page. | AC16: =COUNTIF(Sheet1!$A$1:$A$50,Firms!A16) -> 0
A17: Altaline Capital Management, LLC | B17: PE | C17: CA | D17: Los Angeles | E17: https://www.altaline.com | F17: true | O17: Buyout | P17: Business Services, Technology, Financial Services | U17: Active | V17: 2026 | X17: Medium | Y17: No | Z17: 2026-06-07 | AA17: complete | AB17: Seeded from CapIQ export. Numeric fields are regex first-pass — crawler will confirm. capiq_description preserved for AI extraction fallback. | [extractor] Specialist PE firm focused on services sector transformation. Portfolio shows recent active investments (2025-2026) across tech-enabled services, business services, and financial services. Explicit focus areas documented on website covering vertical market software, essential services, and niche financial services. HQ: 1925 Century Park East, Suite 1700, Los Angeles, CA 90067. US-focused based on portfolio companies and stated service area focus. | AC17: =COUNTIF(Sheet1!$A$1:$A$50,Firms!A17) -> 0
A18: Altaris, LLC | B18: PE | E18: https://www.altariscap.com | F18: true | O18: Buyout | P18: Healthcare | T18: 9000.0 | U18: Active | X18: Medium | Y18: No | Z18: 2026-06-07 | AA18: complete | AB18: Seeded from CapIQ export. Numeric fields are regex first-pass — crawler will confirm. capiq_description preserved for AI extraction fallback. | [extractor] Altaris is a healthcare-focused PE firm founded in 2003 with $9B+ AUM as of June 2025. Exclusively invests in healthcare industry across three subsectors: medical devices/diagnostics, pharmaceuticals/life sciences, and tech-enabled services. 11 active operating companies cited. Over 50 cumulative investments made. No specific investment size, revenue/EBITDA criteria, or HQ location disclosed on provided pages. US investments confirmed through portfolio companies (Minaris, Sharecare, Solesis). | AC18: =COUNTIF(Sheet1!$A$1:$A$50,Firms!A18) -> 0
A19: Amberjack Capital Partners, L.P. | B19: PE | C19: Texas | D19: Houston | E19: https://www.amberjackcapital.com | F19: true | I19: 4.0 | J19: 20.0 | K19: 20.0 | L19: 175.0 | M19: 20.0 | N19: 75.0 | O19: Buyout | P19: Industrials, Infrastructure, Business Services | T19: 1231.38 | U19: Active | X19: High | Y19: No | Z19: 2026-06-07 | AA19: complete | AB19: Seeded from CapIQ export. Numeric fields are regex first-pass — crawler will confirm. capiq_description preserved for AI extraction fallback. | [extractor] Lower middle-market PE firm focused on critical infrastructure services and industrial end markets. Investment criteria explicitly stated: $4M–$20M target EBITDA, $20M–$175M typical platform enterprise value, $20M–$75M equity investment over life of investment. Conservative leverage approach. Portfolio page references active and realized investments but specific deal details not provided in source pages. | AC19: =COUNTIF(Sheet1!$A$1:$A$50,Firms!A19) -> 1 | AD19: =SUBSTITUTE(AB19,"Seeded from CapIQ export. Numeric fields are regex first-pass — c","C") -> Crawler will confirm. capiq_description preserved for AI extraction fallback. | [extractor] Lower middle-market PE firm focused on critical infrastructure services and industrial end markets. Investment criteria explicitly stated: $4M–$20M target EBITDA, $20M–$175M typical platform enterprise value, $20M–$75M equity investment over life of investment. Conservative leverage approach. Portfolio page references active and realized investments but specific deal details not provided in source pages.
A20: Angeles Equity Partners, LLC | B20: PE | C20: CA | D20: Los Angeles | E20: https://www.angelesequity.com | F20: primarily | I20: 0 | J20: 40.0 | L20: 375.0 | N20: 150.0 | O20: Buyout | P20: Industrials, Business Services | T20: 1203.12 | U20: Active | V20: 2025-11-01 | X20: High | Y20: No | Z20: 2026-06-07 | AA20: complete | AB20: Seeded from CapIQ export. Numeric fields are regex first-pass — crawler will confirm. capiq_description preserved for AI extraction fallback. | [extractor] Control equity PE firm focused on lower middle market industrial businesses. Invests in niche manufacturing, critical industrial services, and specialty distribution. 50%+ ownership required. EBITDA criteria spans unprofitable to $40M. Enterprise value up to $375M. Geography includes US & Canada. Portfolio shows 16 current/exited investments from 2016–2025, demonstrating active deal flow. Most recent investment November 2025. Firm Overview PDF available: https://www.angelesequity.com/s/AEP-Overview-June-2026.pdf — not parsed. Fund details and exact AUM not disclosed on website. | AC20: =COUNTIF(Sheet1!$A$1:$A$50,Firms!A20) -> 1 | AD20: =SUBSTITUTE(AB20,"Seeded from CapIQ export. Numeric fields are regex first-pass — c","C") -> Crawler will confirm. capiq_description preserved for AI extraction fallback. | [extractor] Control equity PE firm focused on lower middle market industrial businesses. Invests in niche manufacturing, critical industrial services, and specialty distribution. 50%+ ownership required. EBITDA criteria spans unprofitable to $40M. Enterprise value up to $375M. Geography includes US & Canada. Portfolio shows 16 current/exited investments from 2016–2025, demonstrating active deal flow. Most recent investment November 2025. Firm Overview PDF available: https://www.angelesequity.com/s/AEP-Overview-June-2026.pdf — not parsed. Fund details and exact AUM not disclosed on website.
A21: Antin Infrastructure Partners SAS (ENXTPA:ANTIN) | B21: PE | E21: https://www.antin-ip.com | F21: primarily | M21: 50.0 | N21: 300.0 | O21: Buyout | P21: Infrastructure, Energy | T21: 39685.34 | U21: Active | X21: High | Y21: No | Z21: 2026-06-07 | AA21: complete | AB21: Seeded from CapIQ export. Numeric fields are regex first-pass — crawler will confirm. capiq_description preserved for AI extraction fallback. | [extractor] Infrastructure PE firm based in France (ENXTPA listing ticker). Multiple fund strategies identified: Flagship, Mid Cap (€50m-300m check sizes), and NextGen. Mid Cap strategy explicitly targets Europe and North America across energy & environment, digital, transport, and social infrastructure sectors. Check sizes converted from EUR to USD using mid-range approximation (€50m≈$54m, €300m≈$325m, presented as 50.0-300.0 reflecting EUR amounts). HQ city not explicitly stated in provided pages. No explicit AUM or recent deal dates found in source material. | AC21: =COUNTIF(Sheet1!$A$1:$A$50,Firms!A21) -> 0
A22: Apollo Global Management, Inc. (NYSE:APO) | B22: PE | E22: https://www.apollo.com/institutional/homepage | F22: true | O22: Buyout | P22: Real Estate, Energy, Infrastructure | T22: 938406.0 | U22: Active | V22: 2025-12-01 | X22: Medium | Y22: No | Z22: 2026-06-07 | AA22: complete | AB22: Seeded from CapIQ export. Numeric fields are regex first-pass — crawler will confirm. capiq_description preserved for AI extraction fallback. | [extractor] Apollo Global Management (NYSE:APO) is a diversified asset manager with PE-focused Real Assets platform. Content confirms investment activity in Real Estate, Infrastructure (control-oriented acquisitions, corporate carveouts in mid-market North America/Europe), and Energy Transition/Renewable Energy. Recent deal noted: $6.5B commitment to Ørsted's Hornsea 3 (Dec 2025). Case studies show $565M InterPark mortgage (2021) and Project Helix NPL acquisition (2018). HQ city/state and specific AUM not provided in source. Confidence Medium due to lack of explicit fund-level details and investment criteria thresholds. | AC22: =COUNTIF(Sheet1!$A$1:$A$50,Firms!A22) -> 1 | AD22: =SUBSTITUTE(AB22,"Seeded from CapIQ export. Numeric fields are regex first-pass — c","C") -> Crawler will confirm. capiq_description preserved for AI extraction fallback. | [extractor] Apollo Global Management (NYSE:APO) is a diversified asset manager with PE-focused Real Assets platform. Content confirms investment activity in Real Estate, Infrastructure (control-oriented acquisitions, corporate carveouts in mid-market North America/Europe), and Energy Transition/Renewable Energy. Recent deal noted: $6.5B commitment to Ørsted's Hornsea 3 (Dec 2025). Case studies show $565M InterPark mortgage (2021) and Project Helix NPL acquisition (2018). HQ city/state and specific AUM not provided in source. Confidence Medium due to lack of explicit fund-level details and investment criteria thresholds.
A23: Appian Way Capital Partners, LLC. | B23: PE | C23: TX | D23: Dallas | E23: https://www.appianwaycap.com | F23: true | G23: 10.0 | H23: 100.0 | I23: 2.0 | J23: 10.0 | M23: 10.0 | N23: 50.0 | O23: Buyout, Growth Equity | P23: Industrials, Business Services | U23: Active | X23: High | Y23: No | Z23: 2026-06-07 | AA23: complete | AB23: Seeded from CapIQ export. Numeric fields are regex first-pass — crawler will confirm. capiq_description preserved for AI extraction fallback. | [extractor] Dallas-based PE firm with explicit investment criteria. Focus on Aerospace & Defense, Manufacturing, and Distribution sectors. Targets US-based companies with $10-100M+ revenue and $2-10M+ EBITDA ($4-8M sweet spot). Invests $10-50M initially with capacity for larger checks. Prefers majority or meaningful minority stakes. Growth-focused with hands-on operational involvement; maintains 5-6 portfolio companies. Portfolio includes Gemco Manufacturing (A&D precision parts) and Integrated Field Solutions (industrial automation). Copyright notice shows 2020 date but website appears current. | AC23: =COUNTIF(Sheet1!$A$1:$A$50,Firms!A23) -> 0
A24: Applied Real Intelligence LLC | B24: Other | E24: https://arivc.com | P24: Energy, Healthcare, Industrials | U24: Active | X24: Low | Y24: Yes | Z24: 2026-06-07 | AA24: complete | AB24: Seeded from CapIQ export. Numeric fields are regex first-pass — crawler will confirm. capiq_description preserved for AI extraction fallback. | [extractor] Page content is primarily HTML/CSS boilerplate and JavaScript code. No investment criteria, fund details, or operational information could be extracted. The firm tagline 'You built it; A.R.I. helps you keep it' suggests post-acquisition services but firm type, geography, investment focus, and deal criteria remain unconfirmed. Full page content review needed or access to additional pages required. | AC24: =COUNTIF(Sheet1!$A$1:$A$50,Firms!A24) -> 0
A25: Ara Partners Group, LLC | B25: Other | E25: https://www.arapartners.com | P25: Energy, Industrials, Consumer | T25: 6600.0 | U25: Active | X25: Low | Y25: Yes | Z25: 2026-06-07 | AA25: complete | AB25: Seeded from CapIQ export. Numeric fields are regex first-pass — crawler will confirm. capiq_description preserved for AI extraction fallback. | [extractor] Source page provided contains only HTML boilerplate, CSS, and structured metadata. No substantive investment criteria, fund details, or operational information present. Full website content not provided. Unable to extract any confirmable data. | AC25: =COUNTIF(Sheet1!$A$1:$A$50,Firms!A25) -> 0
A26: Arcapita Group Holdings Limited | B26: PE | E26: https://www.arcapita.com | F26: primarily | O26: Buyout | P26: Real Estate, Business Services, Industrials | U26: Slowing | X26: Medium | Y26: No | Z26: 2026-06-07 | AA26: complete | AB26: Seeded from CapIQ export. Numeric fields are regex first-pass — crawler will confirm. capiq_description preserved for AI extraction fallback. | [extractor] Arcapita is an active PE investor with diversified portfolio across real estate (industrial logistics, rental housing, data centers), business services, and growth capital (fintech, AI). Significant US and global presence evidenced by active investments. Headquarters location not extracted from provided content. Check size, revenue criteria, and fund-specific details not available on this investments page. | AC26: =COUNTIF(Sheet1!$A$1:$A$50,Firms!A26) -> 0
A27: ArchiMed SAS | B27: PE | E27: https://www.archimed.group | P27: Healthcare | T27: 8676.79 | U27: Active | X27: Medium | Y27: Yes | Z27: 2026-06-07 | AA27: complete | AB27: Seeded from CapIQ export. Numeric fields are regex first-pass — crawler will confirm. capiq_description preserved for AI extraction fallback. | [extractor] ArchiMed SAS is a French PE firm focused on healthcare industries (human, animal, environmental health). Only company portfolio page was provided with minimal criteria details. Missing: HQ location specifics, fund details, investment check sizes, revenue/EBITDA targets, deal types, and US investment focus. Needs review of main investment criteria page or fund documentation. | AC27: =COUNTIF(Sheet1!$A$1:$A$50,Firms!A27) -> 0
A28: Arcline Investment Management LP | B28: PE | E28: https://www.arcline.com | F28: primarily | O28: Buyout | P28: Industrials, Technology, Healthcare | T28: 30000.0 | U28: Active | V28: 2026-03-01 | X28: Medium | Y28: No | Z28: 2026-06-07 | AA28: complete | AB28: Seeded from CapIQ export. Numeric fields are regex first-pass — crawler will confirm. capiq_description preserved for AI extraction fallback. | [extractor] Arcline is a growth-oriented PE firm with $30B AUM focused on building industrial platforms through acquisitions. Portfolio of 160+ acquisitions since 2018 across aerospace & defense, engineered components, critical infrastructure, and test & measurement. Mostly US-focused with some European holdings. Buyout/platform strategy with long-term compounding approach. HQ location not specified on page. | AC28: =COUNTIF(Sheet1!$A$1:$A$50,Firms!A28) -> 0
A29: Arkview Capital, L.P. | B29: PE | C29: Connecticut | D29: Stamford | E29: https://www.arkviewcapital.com | F29: true | O29: Buyout | P29: Business Services, Industrials, Financial Services | U29: Active | X29: Medium | Y29: No | Z29: 2026-06-07 | AA29: complete | AB29: Seeded from CapIQ export. Numeric fields are regex first-pass — crawler will confirm. capiq_description preserved for AI extraction fallback. | [extractor] Arkview Capital founded 2020 by Vijay Mehta and two partners. Invests in overlooked, underutilized assets with focus on three sectors: essential businesses, transportation, and financial services. Demonstrated real estate portfolio (parking facilities) in major US metros (Philadelphia, San Diego, Dallas, New York, Memphis). Prior leadership experience in PE (TPG), investment banking (Morgan Stanley), and asset management (ZBI). All investments appear US-based. Confidence medium due to lack of explicit fund size, check size, EBITDA/revenue targets, or formal investment criteria documentation. | AC29: =COUNTIF(Sheet1!$A$1:$A$50,Firms!A29) -> 0
A30: Arlington Management Employees, LLC | B30: PE | E30: https://arlingtoncap.com | O30: Buyout | P30: Healthcare, Industrials, Consumer | T30: 18194.6 | U30: Active | X30: Medium | Y30: Yes | Z30: 2026-06-07 | AA30: complete | AB30: Seeded from CapIQ export. Numeric fields are regex first-pass — crawler will confirm. capiq_description preserved for AI extraction fallback. | [extractor] Firm name is Arlington Capital Partners (ACP), not Arlington Management Employees LLC as provided. Strategy page indicates PE investment focus on government-regulated industries with domain expertise. Minimal structured criteria data extracted from page source. Full investment criteria not visible in provided content. Requires additional source pages or documentation for complete data extraction. | AC30: =COUNTIF(Sheet1!$A$1:$A$50,Firms!A30) -> 0
A31: Arsenal Capital Management LP | B31: PE | E31: https://www.arsenalcapital.com | P31: Healthcare | T31: 9715.62 | U31: Active | X31: Low | Y31: Yes | Z31: 2026-06-07 | AA31: complete | AB31: Seeded from CapIQ export. Numeric fields are regex first-pass — crawler will confirm. capiq_description preserved for AI extraction fallback. | [extractor] Source page is a portfolio page for Arsenal Capital Management LP showing healthcare investments, but the provided content is primarily CSS/JavaScript code with no readable investment criteria, deal details, or firm information extracted. No headquarters location, fund details, investment size ranges, deal types, or other specific criteria could be confirmed. Requires review of actual firm website homepage or investment criteria documentation. | AC31: =COUNTIF(Sheet1!$A$1:$A$50,Firms!A31) -> 0
A32: Artemis Capital Partners Management Co., LLC | B32: PE | C32: MA | D32: Boston | E32: https://www.artemislp.com | F32: true | O32: Buyout | P32: Industrials, Technology | U32: Active | X32: Medium | Y32: No | Z32: 2026-06-07 | AA32: complete | AB32: Seeded from CapIQ export. Numeric fields are regex first-pass — crawler will confirm. capiq_description preserved for AI extraction fallback. | [extractor] Boston-based PE firm focused on buying and building differentiated manufacturers of Industrial Tech. Explicit focus on control acquisitions (buyouts) of engineered product manufacturers with mission-critical applications. Portfolio includes companies in aerospace, life sciences, defense, and semiconductor sectors. Clear technology focus areas: analytical instruments, RF/microwave, testing & measurement, thermal management, optics & photonics, and diagnostics & discovery. Portfolio shows active investments. No fund-level financial data (AUM, check size, vintage year) found on provided pages. | AC32: =COUNTIF(Sheet1!$A$1:$A$50,Firms!A32) -> 0
A33: Ashe Beach Companies | B33: Fundless Sponsor | E33: https://www.ashebeach.com | F33: true | G33: 10.0 | H33: 50.0 | O33: Buyout | P33: Business Services | X33: High | Y33: No | Z33: 2026-06-07 | AA33: complete | AB33: Seeded from CapIQ export. Numeric fields are regex first-pass — crawler will confirm. capiq_description preserved for AI extraction fallback. | [extractor] Independent sponsor (fundless) focused on lower middle market B2B services buyouts. Revenue range $10M-$50M+, requires 15%+ EBITDA margin, asset light model with recurring revenue. Team led by Cliff Goins IV with 25+ years experience; affiliated with EG Collective network. HQ location not specified on website. | AC33: =COUNTIF(Sheet1!$A$1:$A$50,Firms!A33) -> 0
A34: Astira Capital Partners LP | B34: PE | E34: https://www.astiracp.com | F34: true | O34: Buyout, Growth Equity | P34: Financial Services, Technology, Business Services | T34: 777.32 | U34: Active | V34: 2025 | W34: Astira Capital Partners Fund I LP | X34: Medium | Y34: No | Z34: 2026-06-07 | AA34: complete | AB34: Seeded from CapIQ export. Numeric fields are regex first-pass — crawler will confirm. capiq_description preserved for AI extraction fallback. | [extractor] PE firm explicitly states 'Control Buyout or Significant Minority Growth Capital' investment strategy. Portfolio shows recent deals in 2024-2025 across Financial Services, MarTech, and related verticals. Sector focus: Financial Services & FinTech, Government Services & GovTech, Human Capital Management, IT Services, Marketing Services & MarTech, Risk Management & Compliance. Four portfolio companies identified (Numera, CallRevu, Altus, ConData). Headquarters location not explicitly stated on provided pages. | AC34: =COUNTIF(Sheet1!$A$1:$A$50,Firms!A34) -> 0
A35: Atlas FRM LLC | B35: PE | E35: https://www.atlasholdingsllc.com | F35: true | O35: Buyout, Distressed | P35: Industrials, Business Services, Consumer | T35: 18115.02 | U35: Active | X35: Medium | Y35: No | Z35: 2026-06-07 | AA35: complete | AB35: Seeded from CapIQ export. Numeric fields are regex first-pass — crawler will confirm. capiq_description preserved for AI extraction fallback. | [extractor] Atlas Holdings LLC (not Atlas FRM LLC as specified in query—note name discrepancy). PE firm specializing in buyouts and complex distressed/restructuring situations. Invests in operating companies with operational/financial challenges across 12 specified industrial sectors. Has completed 300+ transactions including bankruptcies, carve-outs, restructurings. UK subsidiary Atlas FRM (UK) Limited noted. No HQ location, AUM, fund vintage, or check size data found. Activity appears active based on website. Confidence medium due to limited financial/fund-specific data. Needs review: firm name mismatch in query. | AC35: =COUNTIF(Sheet1!$A$1:$A$50,Firms!A35) -> 0
A36: Audax Management Company, LLC | B36: PE | E36: https://www.audaxprivateequity.com | F36: primarily | I36: 5.0 | J36: 100.0 | L36: 1000.0 | O36: Buyout | P36: Business Services, Consumer, Healthcare | Q36: Financial Services, Industrials, Technology | T36: 19950.28 | U36: Active | X36: High | Y36: No | Z36: 2026-06-07 | AA36: complete | AB36: Seeded from CapIQ export. Numeric fields are regex first-pass — crawler will confirm. capiq_description preserved for AI extraction fallback. | [extractor] Audax Private Equity firm with Flagship and Origins strategies. Buy & Build approach targeting lower middle market. EBITDA range $5M-$100M, Enterprise Values up to $1B. Portfolio includes US/Canada HQ with operations across five continents. Sectors: Business Services, Consumer, Financial Services, Healthcare, Industrial Services & Technologies, Software & Technology. PDF fact sheet available but binary content not fully parsed. | AC36: =COUNTIF(Sheet1!$A$1:$A$50,Firms!A36) -> 1 | AD36: =SUBSTITUTE(AB36,"Seeded from CapIQ export. Numeric fields are regex first-pass — c","C") -> Crawler will confirm. capiq_description preserved for AI extraction fallback. | [extractor] Audax Private Equity firm with Flagship and Origins strategies. Buy & Build approach targeting lower middle market. EBITDA range $5M-$100M, Enterprise Values up to $1B. Portfolio includes US/Canada HQ with operations across five continents. Sectors: Business Services, Consumer, Financial Services, Healthcare, Industrial Services & Technologies, Software & Technology. PDF fact sheet available but binary content not fully parsed.
A37: Aurelia Capital | B37: Other | E37: https://aureliacap.com | P37: Industrials, Technology | T37: 3520.0 | X37: Low | Y37: Yes | Z37: 2026-06-07 | AA37: complete | AB37: Seeded from CapIQ export. Numeric fields are regex first-pass — crawler will confirm. capiq_description preserved for AI extraction fallback. | [extractor] Source page (https://aureliacap.com/about) contains only CSS/font declarations and no substantive investment criteria data. No firm information, fund details, investment thesis, or financial parameters could be extracted. Requires review of additional pages or documents to populate criteria. | AC37: =COUNTIF(Sheet1!$A$1:$A$50,Firms!A37) -> 0
A38: Aurora Capital Partners | B38: Other | E38: https://www.auroracap.com | P38: Energy, Industrials, Healthcare | T38: 6000.0 | U38: Active | X38: Low | Y38: Yes | Z38: 2026-06-07 | AA38: complete | AB38: Seeded from CapIQ export. Numeric fields are regex first-pass — crawler will confirm. capiq_description preserved for AI extraction fallback. | [extractor] Source page contains only New Relic tracking and analytics code. No investment criteria, fund information, or business details visible. Page at https://www.auroracap.com/Strategy appears to be rendering dynamic content not captured in provided source. | AC38: =COUNTIF(Sheet1!$A$1:$A$50,Firms!A38) -> 0
A39: Author Capital Partners, LLC | B39: PE | C39: IL | D39: Chicago | E39: https://www.authorcapital.com | F39: primarily | I39: 2.0 | J39: 20.0 | M39: 5.0 | N39: 30.0 | O39: Buyout | P39: Generalist | U39: Active | X39: High | Y39: No | Z39: 2026-06-07 | AA39: complete | AB39: Seeded from CapIQ export. Numeric fields are regex first-pass — crawler will confirm. capiq_description preserved for AI extraction fallback. | [extractor] Equity Investment check size $5M-$30M+, EBITDA $2M-$20M confirmed. Invests in US and Canada-based businesses with sustainable competitive advantages and recurring revenue. Focus on family and founder-led businesses with long-term growth prospects. Buy-and-build strategy employed. No fund-specific details, AUM, or recent deal dates found on provided pages. | AC39: =COUNTIF(Sheet1!$A$1:$A$50,Firms!A39) -> 1 | AD39: =SUBSTITUTE(AB39,"Seeded from CapIQ export. Numeric fields are regex first-pass — c","C") -> Crawler will confirm. capiq_description preserved for AI extraction fallback. | [extractor] Equity Investment check size $5M-$30M+, EBITDA $2M-$20M confirmed. Invests in US and Canada-based businesses with sustainable competitive advantages and recurring revenue. Focus on family and founder-led businesses with long-term growth prospects. Buy-and-build strategy employed. No fund-specific details, AUM, or recent deal dates found on provided pages.
A40: Avem Partners | B40: PE | D40: Southern California | E40: https://www.avempartners.com | F40: primarily | G40: 15.0 | H40: 200.0 | I40: 3.0 | K40: 15.0 | L40: 150.0 | M40: 10.0 | N40: 50.0 | O40: Buyout | P40: Industrials | U40: Active | X40: High | Y40: No | Z40: 2026-06-07 | AA40: complete | AB40: Seeded from CapIQ export. Numeric fields are regex first-pass — crawler will confirm. capiq_description preserved for AI extraction fallback. | [extractor] Avem Partners is a PE firm exclusively focused on aerospace/defense lower middle market companies in North America. Founded 2017. Investment criteria explicitly stated: $10-50M check size, $15-150M EV, $15-200M revenue, $3M+ EBITDA. Deal structure involves majority control, limited leverage. HQ stated as 'Southern California' but specific city/state not provided. Multiple realized investments listed (Spencer Aerospace, Synchronous Aerospace Group, Advent Aerospace, Aero Pacific, Drilltec, Resco, Alloy Processing); no unrealized investment details visible on provided pages. | AC40: =COUNTIF(Sheet1!$A$1:$A$50,Firms!A40) -> 1 | AD40: =SUBSTITUTE(AB40,"Seeded from CapIQ export. Numeric fields are regex first-pass — c","C") -> Crawler will confirm. capiq_description preserved for AI extraction fallback. | [extractor] Avem Partners is a PE firm exclusively focused on aerospace/defense lower middle market companies in North America. Founded 2017. Investment criteria explicitly stated: $10-50M check size, $15-150M EV, $15-200M revenue, $3M+ EBITDA. Deal structure involves majority control, limited leverage. HQ stated as 'Southern California' but specific city/state not provided. Multiple realized investments listed (Spencer Aerospace, Synchronous Aerospace Group, Advent Aerospace, Aero Pacific, Drilltec, Resco, Alloy Processing); no unrealized investment details visible on provided pages.
A41: Avesi Partners, LLC. | B41: Other | E41: https://avesipartners.com | P41: Healthcare, Industrials | T41: 3154.09 | U41: Active | X41: Low | Y41: Yes | Z41: 2026-06-07 | AA41: complete | AB41: Seeded from CapIQ export. Numeric fields are regex first-pass — crawler will confirm. capiq_description preserved for AI extraction fallback. | [extractor] Portfolio page accessed but contains only navigation structure and form code with no actual investment criteria, portfolio company details, or fund information. Page title indicates 'Current Investments' section exists but content not provided in source. Requires review of full website pages (About, Investment Approach) to extract criteria. | AC41: =COUNTIF(Sheet1!$A$1:$A$50,Firms!A41) -> 0
A42: Avista Capital Holdings, L.P. | B42: PE | E42: https://www.avistahealthcare.com | P42: Healthcare | T42: 6658.42 | U42: Active | X42: Low | Y42: Yes | Z42: 2026-06-07 | AA42: complete | AB42: Seeded from CapIQ export. Numeric fields are regex first-pass — crawler will confirm. capiq_description preserved for AI extraction fallback. | [extractor] Source page is Avista Healthcare (avistahealthcare.com), an 'Approach' page that only contains boilerplate HTML/CSS with no actual investment criteria, fund details, or portfolio information. Firm appears to be healthcare-focused PE based on URL and organization name, but insufficient data to confirm deal types, check sizes, AUM, or other material criteria. Full page content needed for accurate extraction. | AC42: =COUNTIF(Sheet1!$A$1:$A$50,Firms!A42) -> 0
A43: B-Flexion Advisors (UK) LLP | B43: Family Office | D43: Geneva | E43: https://www.bflexion.com/businesses/b-flexion-advisors-uk-llp | F43: true | O43: Buyout, Other | P43: Healthcare, Technology, Real Estate | U43: Active | V43: 2019 | X43: Medium | Y43: No | Z43: 2026-06-07 | AA43: complete | AB43: Seeded from CapIQ export. Numeric fields are regex first-pass — crawler will confirm. capiq_description preserved for AI extraction fallback. | [extractor] B-FLEXION is a multi-generational family office founded by Ernesto Bertarelli (Serono pharmaceutical heir). Operates as an umbrella investment vehicle managing multiple asset managers (Kedge Capital, Crosstree Real Estate, Northill Capital, Forestay Capital, Gurnet Point Capital, Strategic Investment Group) and direct operating company holdings (Affidea, Stallergenes Greer, Campus Biotech). Primary sectors: Life Sciences, Healthcare Services, Digital Health, Real Estate, Technology. Has offices across Europe and US. Most recent verifiable deal activity: 2019 (Stallergenes Greer acquisition). Specific fund vehicles, AUM, and investment cheque sizes not disclosed on available pages. | AC43: =COUNTIF(Sheet1!$A$1:$A$50,Firms!A43) -> 0
A44: BIP Wealth, LLC | B44: Other | E44: https://bipwealth.com | P44: Financial Services, Healthcare, Consumer | U44: Active | X44: Low | Y44: Yes | Z44: 2026-06-07 | AA44: complete | AB44: Seeded from CapIQ export. Numeric fields are regex first-pass — crawler will confirm. capiq_description preserved for AI extraction fallback. | [extractor] Source page appears to be a financial advisory website (Georgia Financial Advisors) with only technical code visible. No investment criteria, fund details, deal types, sectors, check sizes, AUM, or PE/VC-related information could be extracted. Page content is truncated and does not contain substantive business information. Firm may be a financial advisory service rather than PE/VC investor. Requires review of actual content. | AC44: =COUNTIF(Sheet1!$A$1:$A$50,Firms!A44) -> 0
A45: Bain Capital Double Impact | B45: PE | C45: MA | D45: Boston | E45: https://www.baincapitaldoubleimpact.com | F45: Yes | M45: 50.0 | N45: 200.0 | O45: Buyout | P45: Generalist | T45: 2600.0 | U45: Active | W45: Double Impact | X45: High | Y45: No | Z45: 2026-06-07 | AA45: complete | AB45: Seeded from CapIQ export. Numeric fields are regex first-pass — crawler will confirm. capiq_description preserved for AI extraction fallback. | [extractor] Bain Capital Double Impact is a PE fund focused on control buyouts ($50-200M+ check sizes) of mission-driven, growing companies with positive social and environmental impact. Founded 1984, headquartered Boston. Targets control opportunities. Impact documents available (OPIM Disclosure, BlueMark verification PDFs) but not parsed for additional criteria. No sector restrictions found; generalist focus on impact-aligned businesses. | AC45: =COUNTIF(Sheet1!$A$1:$A$50,Firms!A45) -> 0
A46: Bain Capital Private Equity, LP | B46: PE | E46: https://www.baincapitalprivateequity.com | P46: Financial Services, Real Estate, Energy | U46: Active | X46: Low | Y46: Yes | Z46: 2026-06-07 | AA46: complete | AB46: Seeded from CapIQ export. Numeric fields are regex first-pass — crawler will confirm. capiq_description preserved for AI extraction fallback. | [extractor] Source page contained only HTML boilerplate and cookie policy elements; no substantive investment criteria, strategy, sector focus, or deal parameters were extractable. Full page content analysis required from actual strategy page content. | AC46: =COUNTIF(Sheet1!$A$1:$A$50,Firms!A46) -> 0
A47: Bain Capital, LP | B47: PE | C47: MA | D47: Boston | E47: https://www.baincapital.com | F47: true | O47: Buyout, Growth Equity, Venture | P47: Generalist | T47: 215000.0 | U47: Active | V47: 2026-06-07 | X47: Medium | Y47: No | Z47: 2026-06-07 | AA47: complete | AB47: Seeded from CapIQ export. Numeric fields are regex first-pass — crawler will confirm. capiq_description preserved for AI extraction fallback. | [extractor] Bain Capital is a diversified global investment firm with multiple platforms: Private Equity (Global PE, Double Impact, Insurance), Growth & Venture (Ventures, Life Sciences, Tech Opportunities, Crypto), Capital Solutions (Special Situations), Credit, and Real Assets (Real Estate). Founded 1984, headquartered Boston. Recent deal activity confirmed (Asia Fund VI close June 2026, $10.5B raised). AUM figure listed as ~$0B on page (appears to be placeholder). Specific investment criteria, check sizes, and sector preferences not provided on this page. Multi-platform structure suggests Generalist approach. needs_review=true due to incomplete AUM data and lack of specific criteria details. | AC47: =COUNTIF(Sheet1!$A$1:$A$50,Firms!A47) -> 1 | AD47: =SUBSTITUTE(AB47,"Seeded from CapIQ export. Numeric fields are regex first-pass — c","C") -> Crawler will confirm. capiq_description preserved for AI extraction fallback. | [extractor] Bain Capital is a diversified global investment firm with multiple platforms: Private Equity (Global PE, Double Impact, Insurance), Growth & Venture (Ventures, Life Sciences, Tech Opportunities, Crypto), Capital Solutions (Special Situations), Credit, and Real Assets (Real Estate). Founded 1984, headquartered Boston. Recent deal activity confirmed (Asia Fund VI close June 2026, $10.5B raised). AUM figure listed as ~$0B on page (appears to be placeholder). Specific investment criteria, check sizes, and sector preferences not provided on this page. Multi-platform structure suggests Generalist approach. needs_review=true due to incomplete AUM data and lack of specific criteria details.
A48: Baird Capital | B48: PE | E48: https://www.bairdcapital.com | F48: true | O48: Buyout | P48: Generalist | T48: 1600.0 | U48: Active | V48: 2024-08-01 | X48: Medium | Y48: No | Z48: 2026-06-07 | AA48: complete | AB48: Seeded from CapIQ export. Numeric fields are regex first-pass — crawler will confirm. capiq_description preserved for AI extraction fallback. | [extractor] Portfolio page confirms PE firm with $1.6B AUM, inception 1989, 40+ professionals. Diverse portfolio across multiple geographies (US, UK, Asia) and sectors suggests generalist approach. Last confirmed deal: BlackCloak (Aug 2024). HQ location not explicitly stated on this page. Venture Capital strategy also mentioned in navigation but no venture-specific portfolio details provided on this page. Needs review to clarify HQ location and confirm deal type mix. | AC48: =COUNTIF(Sheet1!$A$1:$A$50,Firms!A48) -> 0
A49: Balmoral Funds LLC | B49: PE | C49: CA | D49: Los Angeles | E49: https://www.balmoralfunds.com | F49: true | G49: 30.0 | H49: 800.0 | M49: 10.0 | N49: 100.0 | O49: Buyout, Recap | P49: Industrials, Business Services, Consumer | T49: 1300.0 | U49: Active | V49: 2025-12-09 | X49: High | Y49: No | Z49: 2026-06-07 | AA49: complete | AB49: Seeded from CapIQ export. Numeric fields are regex first-pass — crawler will confirm. capiq_description preserved for AI extraction fallback. | [extractor] Special situations PE firm focused on control and shared-control investments. Investment criteria explicitly stated on website. Portfolio includes diversified industrial, logistics, and specialty manufacturing companies. Recent deals through December 2025. Fact sheet PDF available at https://www.balmoralfunds.com/wp-content/uploads/Balmoral-Fact-Sheet-03-23-2026.pdf but not parsed. Sectors inferred from portfolio companies (aviation, logistics, modular construction, specialty chemicals). No AUM, fund vintage, or explicit sector exclusions disclosed. | AC49: =COUNTIF(Sheet1!$A$1:$A$50,Firms!A49) -> 1 | AD49: =SUBSTITUTE(AB49,"Seeded from CapIQ export. Numeric fields are regex first-pass — c","C") -> Crawler will confirm. capiq_description preserved for AI extraction fallback. | [extractor] Special situations PE firm focused on control and shared-control investments. Investment criteria explicitly stated on website. Portfolio includes diversified industrial, logistics, and specialty manufacturing companies. Recent deals through December 2025. Fact sheet PDF available at https://www.balmoralfunds.com/wp-content/uploads/Balmoral-Fact-Sheet-03-23-2026.pdf but not parsed. Sectors inferred from portfolio companies (aviation, logistics, modular construction, specialty chemicals). No AUM, fund vintage, or explicit sector exclusions disclosed.
A50: Banneker Partners, LLC | B50: PE | E50: https://www.bannekerpartners.com | O50: Buyout | P50: Technology | U50: Active | X50: Medium | Y50: Yes | Z50: 2026-06-07 | AA50: complete | AB50: Seeded from CapIQ export. Numeric fields are regex first-pass — crawler will confirm. capiq_description preserved for AI extraction fallback. | [extractor] Page content extracted focuses on investment approach in enterprise software companies. Firm described as 'private equity partner specialized in software investing.' Limited data available—no HQ location, check size, AUM, fund details, or recent deal dates confirmed. Page is primarily CSS and schema markup with minimal substantive criteria. Requires additional source pages (team, portfolio, fund documents) for comprehensive profile. | AC50: =COUNTIF(Sheet1!$A$1:$A$50,Firms!A50) -> 0
A51: Bansk Group LLC | B51: PE | C51: NY | D51: New York | E51: https://www.banskgroup.com | F51: true | M51: 100.0 | N51: 400.0 | O51: Buyout | P51: Consumer | T51: 2000.0 | U51: Active | X51: High | Y51: No | Z51: 2026-06-07 | AA51: complete | AB51: Seeded from CapIQ export. Numeric fields are regex first-pass — crawler will confirm. capiq_description preserved for AI extraction fallback. | [extractor] Bansk Group founded 2019, consumer-focused PE firm based in New York. Partners have collectively invested $30B+ across 40+ transactions. Target equity check size $100M-$400M. Focus areas: Beauty & Personal Care, Consumer Health, Food & Beverage, Household Products. Current portfolio includes Arcadia (OTC/vitamins/supplements) and BYOMA (skincare). Long-term value creation model with operational expertise. No specific fund name or vintage year for current fund disclosed on website. | AC51: =COUNTIF(Sheet1!$A$1:$A$50,Firms!A51) -> 0
A52: Basalt Infrastructure Partners LLP | B52: PE | D52: London | E52: https://www.basaltinfra.com | F52: true | O52: Buyout | P52: Infrastructure | T52: 9000.0 | U52: Active | X52: Medium | Y52: No | Z52: 2026-06-07 | AA52: complete | AB52: Seeded from CapIQ export. Numeric fields are regex first-pass — crawler will confirm. capiq_description preserved for AI extraction fallback. | [extractor] Basalt Infrastructure Partners is a dedicated mid-market infrastructure PE investor with transatlantic focus (Europe and North America). AUM of $9bn confirmed. 35 investments across Power, Transport, Utilities, Telecom, Waste, Energy, and related infrastructure sectors. Team of 59 professionals with 19 years average senior experience. No specific deal size minimums/maximums, revenue/EBITDA criteria found on website. | AC52: =COUNTIF(Sheet1!$A$1:$A$50,Firms!A52) -> 0
A53: BayHawk Capital, L.P. | B53: PE | C53: MA | D53: Boston | E53: https://www.bayhawkcapital.com | F53: primarily | M53: 25.0 | N53: 150.0 | O53: Buyout, Minority | P53: Technology, Business Services, Industrials | Q53: Essential Services, Infrastructure Services, Tech-Enabled Services | R53: Industrial and Facility Services, Residential and Commercial Services, Testing Inspection Compliance Certification, Data and Information Services, Software-as-a-Service | T53: 730.75 | U53: Active | V53: 2025-12 | X53: High | Y53: No | Z53: 2026-06-07 | AA53: complete | AB53: Seeded from CapIQ export. Numeric fields are regex first-pass — crawler will confirm. capiq_description preserved for AI extraction fallback. | [extractor] Boston-based PE firm founded by former Thomas H. Lee Partners team members. Invests in essential services and technology companies in North America with majority or substantial minority stakes. Check sizes $25-150M. Recent investments through December 2025. Founding team has 50+ years combined experience and deployed $4B+ across sectors. No specific fund vintage, AUM, or fund number disclosed on website. | AC53: =COUNTIF(Sheet1!$A$1:$A$50,Firms!A53) -> 0
A54: BayPine LP | B54: PE | C54: Massachusetts | D54: Boston | E54: https://www.baypine.com | F54: true | O54: Buyout | P54: Healthcare, Industrials, Business Services | T54: 2941.8 | U54: Active | V54: 2025 | X54: Medium | Y54: No | Z54: 2026-06-07 | AA54: complete | AB54: Seeded from CapIQ export. Numeric fields are regex first-pass — crawler will confirm. capiq_description preserved for AI extraction fallback. | [extractor] BayPine is a PE firm focused on digitization and modernization of traditional businesses. HQ Boston with NYC office. Portfolio spans Healthcare Services (QualDerm, CenExel), Industrial Services (Mavis, POLYWOOD), and Business Services (Penn Foster, Harbor). All portfolio companies marked Unrealized; most recent deal 2025. Investment criteria emphasize tech-enabled growth, market-leading businesses, and digital transformation. No explicit fund sizing, AUM, check size, or financial metric thresholds found on website. | AC54: =COUNTIF(Sheet1!$A$1:$A$50,Firms!A54) -> 0
A55: Berkshire Partners LLC | B55: PE | E55: https://berkshirepartners.com | P55: Financial Services, Real Estate, Healthcare | T55: 29003.5 | U55: Active | X55: Low | Y55: Yes | Z55: 2026-06-07 | AA55: complete | AB55: Seeded from CapIQ export. Numeric fields are regex first-pass — crawler will confirm. capiq_description preserved for AI extraction fallback. | [extractor] Page content is mostly tracking code and analytics scripts. Only confirmed: firm_type=PE (inferred from URL structure /private-equity/). Meta description states 'In more than three decades of private equity investing' and firm invests in 'growing and enduring businesses' with focus on 'partnerships with management teams', but no specific investment criteria, sectors, check sizes, AUM, or geographic focus extracted. Actual investment criteria content not present in provided source. Needs review of full webpage content. | AC55: =COUNTIF(Sheet1!$A$1:$A$50,Firms!A55) -> 0
A56: Bessemer Investment Partners | B56: PE | C56: NY | D56: New York | E56: https://www.bessemerinvestors.com | F56: true | O56: Buyout | P56: Business Services, Industrials, Real Estate | U56: Active | V56: 2024-09-01 | X56: Medium | Y56: No | Z56: 2026-06-07 | AA56: complete | AB56: Seeded from CapIQ export. Numeric fields are regex first-pass — crawler will confirm. capiq_description preserved for AI extraction fallback. | [extractor] Bessemer Investors is a family-office-backed PE firm (Phipps family capital). Based on portfolio companies, invests in control acquisitions across business services, light industrials, and real estate sectors. Recent deals: W Services Group (Sept 2024), RotoCo (June 2022). No explicit investment criteria ranges found. No fund-specific details (vintage, AUM, check size) available. Describe as 'Partners, Not Owners' with flexible hold periods and no portfolio fees. | AC56: =COUNTIF(Sheet1!$A$1:$A$50,Firms!A56) -> 0
A57: Black Dragon Capital, LLC | B57: PE | E57: https://www.blackdragoncap.com | O57: Venture, Growth Equity, Buyout | P57: Technology | T57: 900.0 | U57: Active | X57: Medium | Y57: No | Z57: 2026-06-07 | AA57: complete | AB57: Seeded from CapIQ export. Numeric fields are regex first-pass — crawler will confirm. capiq_description preserved for AI extraction fallback. | [extractor] Black Dragon Capital invests across early-stage to established technology companies with buyout and growth-oriented mandates. Portfolio companies identified: EnterWorks (e-commerce), Indus, Digital Goodie. Fintech focus area noted. Operationally-led model with deep industry contacts. HQ location, fund details, AUM, check sizes, and specific investment thresholds not disclosed on pages reviewed. No PDF criteria document found. Pages appear incomplete/truncated. Confidence Medium due to inferred deal types from descriptive language rather than explicit criteria statements. | AC57: =COUNTIF(Sheet1!$A$1:$A$50,Firms!A57) -> 0
A58: Blackford Capital Associates II, Inc. | B58: PE | C58: Michigan | D58: Grand Rapids | E58: https://www.blackfordcapital.com | F58: true | O58: Buyout | P58: Industrials, Business Services | T58: 91.07 | U58: Active | V58: 2025-01-27 | W58: Blackford Capital Associates II, Inc. | X58: Medium | Y58: No | Z58: 2026-06-07 | AA58: complete | AB58: Seeded from CapIQ export. Numeric fields are regex first-pass — crawler will confirm. capiq_description preserved for AI extraction fallback. | [extractor] Blackford Capital is a lower middle market PE firm headquartered in Grand Rapids, Michigan. Portfolio evidence shows active buyout activity across industrial, construction services, fire safety, and automation sectors. Recent deals include Security Fire Systems (Dec 2024), Texas Injection Molding (2026), Ace Controls (Jan 2025), and Mopec sale (Jan 2025). No explicit investment criteria, AUM, check size, or financial thresholds found on portfolio page. Fund number inferred from firm name suffix 'II'. | AC58: =COUNTIF(Sheet1!$A$1:$A$50,Firms!A58) -> 0
A59: Blackstone Energy Transition Partners | B59: PE | E59: https://www.blackstone.com/our-businesses/blackstone-energy-transition-partners | F59: primarily | O59: Buyout | P59: Energy, Industrials, Infrastructure | T59: 5600.0 | U59: Slowing | W59: Blackstone Energy Transition Partners IV | X59: Medium | Y59: No | Z59: 2026-06-07 | AA59: complete | AB59: Seeded from CapIQ export. Numeric fields are regex first-pass — crawler will confirm. capiq_description preserved for AI extraction fallback. | [extractor] Blackstone Energy Transition Partners is a PE firm focused on energy transition and climate solutions. BETP IV closed at $5.6B hard cap (approximately 33% larger than predecessor). Firm has invested over $28B globally across energy sectors. Portfolio includes power plants, grid infrastructure, SaaS platforms, engineering services, and renewable energy. Headquarters location not specified on page. | AC59: =COUNTIF(Sheet1!$A$1:$A$50,Firms!A59) -> 0
A60: Blackstone Inc. (NYSE:BX) | B60: PE | E60: https://www.blackstone.com | O60: Buyout | P60: Real Estate, Infrastructure, Generalist | T60: 1274931.23 | U60: Active | X60: Medium | Y60: No | Z60: 2026-06-07 | AA60: complete | AB60: Seeded from CapIQ export. Numeric fields are regex first-pass — crawler will confirm. capiq_description preserved for AI extraction fallback. | [extractor] Blackstone is a publicly traded diversified alternative asset manager (NYSE:BX) with multiple business lines including Private Equity, Real Estate, Credit & Insurance, Infrastructure, Life Sciences, Growth, and Energy Transition Partners. Website is corporate overview; specific investment criteria not detailed. HQ location not confirmed from provided content. AUM and specific fund information not extracted from homepage. Requires review of individual business unit pages or investor materials for detailed criteria. | AC60: =COUNTIF(Sheet1!$A$1:$A$50,Firms!A60) -> 1 | AD60: =SUBSTITUTE(AB60,"Seeded from CapIQ export. Numeric fields are regex first-pass — c","C") -> Crawler will confirm. capiq_description preserved for AI extraction fallback. | [extractor] Blackstone is a publicly traded diversified alternative asset manager (NYSE:BX) with multiple business lines including Private Equity, Real Estate, Credit & Insurance, Infrastructure, Life Sciences, Growth, and Energy Transition Partners. Website is corporate overview; specific investment criteria not detailed. HQ location not confirmed from provided content. AUM and specific fund information not extracted from homepage. Requires review of individual business unit pages or investor materials for detailed criteria.
A61: Blue Sage Capital, L.P. | B61: PE | C61: TX | D61: Austin | E61: https://www.bluesage.com | F61: true | I61: 5.0 | J61: 25.0 | M61: 25.0 | N61: 60.0 | O61: Buyout, Growth Equity, Recap, Mezzanine | P61: Industrials, Business Services | T61: 1000.0 | U61: Active | V61: 2025-11-05 | W61: Blue Sage Capital IV, L.P. | X61: High | Y61: No | Z61: 2026-06-07 | AA61: complete | AB61: Seeded from CapIQ export. Numeric fields are regex first-pass — crawler will confirm. capiq_description preserved for AI extraction fallback. | [extractor] Firm at a Glance PDF available: https://static.spacecrafted.com/c92111026fa443e6b8fe2553197229b3/r/e47e0544e59d424198110dd6cbf5f238/1/Blue%20Sage%20Flyer%20%28%20October%20-%2025%29.pdf — not parsed. AUM stated as 'over a billion dollars' set to 1000.0. Fund IV closed January 2025 at $618M; Blue Sage Strategic Credit Fund closed October 2025 at $287M. Recent deal activity through November 2025 indicates Active status. Check size range inferred from '$25-60M investment' language. Sector keywords extracted from stated industries. Deal types include majority/minority equity and mezzanine debt flexibility per criteria. | AC61: =COUNTIF(Sheet1!$A$1:$A$50,Firms!A61) -> 1 | AD61: =SUBSTITUTE(AB61,"Seeded from CapIQ export. Numeric fields are regex first-pass — c","C") -> Crawler will confirm. capiq_description preserved for AI extraction fallback. | [extractor] Firm at a Glance PDF available: https://static.spacecrafted.com/c92111026fa443e6b8fe2553197229b3/r/e47e0544e59d424198110dd6cbf5f238/1/Blue%20Sage%20Flyer%20%28%20October%20-%2025%29.pdf — not parsed. AUM stated as 'over a billion dollars' set to 1000.0. Fund IV closed January 2025 at $618M; Blue Sage Strategic Credit Fund closed October 2025 at $287M. Recent deal activity through November 2025 indicates Active status. Check size range inferred from '$25-60M investment' language. Sector keywords extracted from stated industries. Deal types include majority/minority equity and mezzanine debt flexibility per criteria.
A62: Bluejay Capital Partners, LLC | B62: Other | E62: https://bluejay-advisors.com | P62: Industrials, Infrastructure, Consumer | U62: Active | X62: Low | Y62: Yes | Z62: 2026-06-07 | AA62: complete | AB62: Seeded from CapIQ export. Numeric fields are regex first-pass — crawler will confirm. capiq_description preserved for AI extraction fallback. | [extractor] Source material is about Bluejay Advisors (grants advisory firm), not Bluejay Capital Partners, LLC. No PE/VC investment criteria found. The website shows grant application advisory services for transportation infrastructure projects, not investment activities. Firm type, location, investment criteria, and fund details cannot be confirmed from provided content. | AC62: =COUNTIF(Sheet1!$A$1:$A$50,Firms!A62) -> 0
A63: Bluestar Alliance, LLC | B63: Other | C63: NY | D63: New York | E63: https://www.bluestaralliance.com/ | P63: Consumer | U63: Active | X63: Medium | Y63: No | Z63: 2026-06-07 | AA63: complete | AB63: Seeded from CapIQ export. Numeric fields are regex first-pass — crawler will confirm. capiq_description preserved for AI extraction fallback. | [extractor] Bluestar Alliance is a brand management company, not a traditional PE/VC firm. Founded 2007. Headquarters inferred as New York (phone 212 area code). Portfolio generates $13B+ in global retail sales. Operates 500+ branded retail stores globally. Not an investment fund; manages consumer brands across fashion, lifestyle, entertainment, home sectors. Investment contact email exists but firm appears to be a brand operator/manager rather than capital allocator. Lacks traditional PE/VC investment criteria. | AC63: =COUNTIF(Sheet1!$A$1:$A$50,Firms!A63) -> 0
A64: Bolt Ventures GmbH | B64: VC | D64: München | E64: https://bolt-ventures.com | F64: false | O64: Venture | P64: Technology | U64: Active | X64: Medium | Y64: No | Z64: 2026-06-07 | AA64: complete | AB64: Seeded from CapIQ export. Numeric fields are regex first-pass — crawler will confirm. capiq_description preserved for AI extraction fallback. | [extractor] Family-owned VC firm focused on IT, Gaming & High Tech companies in Europe with global ambition. Acquires significant shareholdings with active board involvement. Buy & build and organic growth strategies mentioned. No explicit check size, AUM, fund details, or US investment confirmation provided. | AC64: =COUNTIF(Sheet1!$A$1:$A$50,Firms!A64) -> 0
A65: Borgman Capital LLC | B65: PE | C65: IL | D65: Chicago | E65: https://www.borgmancapital.com | F65: primarily | G65: 10.0 | H65: 75.0 | I65: 2.0 | J65: 10.0 | K65: 15.0 | L65: 100.0 | M65: 5.0 | N65: 30.0 | O65: Buyout, Recap | P65: Industrials, Business Services, Healthcare | Q65: Manufacturing, Distribution, Healthcare Services | R65: HVAC, Food Processing, Outsourced Services | S65: Real Estate, Financial Services, Startups | U65: Active | X65: High | Y65: No | Z65: 2026-06-04 | AA65: complete | AB65: Seeded from CapIQ export. Numeric fields are regex first-pass — crawler will confirm. capiq_description preserved for AI extraction fallback. | [crawler] Explicit investment criteria page found. | AC65: =COUNTIF(Sheet1!$A$1:$A$50,Firms!A65) -> 1 | AD65: =SUBSTITUTE(AB65,"Seeded from CapIQ export. Numeric fields are regex first-pass — c","C") -> Crawler will confirm. capiq_description preserved for AI extraction fallback. | [crawler] Explicit investment criteria page found.
A66: Bow River Asset Management LLC | B66: PE | E66: https://www.bowrivercapital.com | F66: true | G66: 25.0 | H66: 200.0 | I66: 7.0 | J66: 25.0 | O66: Buyout, Recap | P66: Industrials, Healthcare, Business Services | U66: Active | V66: 2025-03-05 | X66: High | Y66: No | Z66: 2026-06-07 | AA66: complete | AB66: Seeded from CapIQ export. Numeric fields are regex first-pass — crawler will confirm. capiq_description preserved for AI extraction fallback. | [extractor] Multi-strategy platform with PE, Private Credit, Asset-Based Finance, and other verticals. Extracted PE criteria from Private Equity page. HQ location (Denver, CO inferred from 303 area code) not explicitly confirmed in provided pages. Recent deals through 2025. Platform has ~50+ total deals worth $2.75B. Also operates Software Growth Equity and VC verticals not detailed in provided content. | AC66: =COUNTIF(Sheet1!$A$1:$A$50,Firms!A66) -> 0
A67: Brenton Point Capital Partners, LLC | B67: Other | E67: https://www.brentonpointcp.com | P67: Industrials, Consumer | U67: Active | X67: Low | Y67: Yes | Z67: 2026-06-07 | AA67: complete | AB67: Seeded from CapIQ export. Numeric fields are regex first-pass — crawler will confirm. capiq_description preserved for AI extraction fallback. | [extractor] Portfolio page accessed (https://brentonpointcp.com/portfolio) but only rendered JavaScript/CSS code provided—no actual portfolio company data, investment criteria, or firm details visible. Cannot extract investment criteria without substantive content. Requires review of actual HTML content or alternative source pages. | AC67: =COUNTIF(Sheet1!$A$1:$A$50,Firms!A67) -> 0
A68: Brightstar Capital Partners, L.P. | B68: PE | C68: NY | D68: New York | E68: https://www.brightstarcp.com | F68: true | O68: Buyout | P68: Business Services, Industrials, Technology | T68: 4849.98 | U68: Active | X68: Medium | Y68: No | Z68: 2026-06-07 | AA68: complete | AB68: Seeded from CapIQ export. Numeric fields are regex first-pass — crawler will confirm. capiq_description preserved for AI extraction fallback. | [extractor] PE firm focused on middle market control investments with operational engagement. Multiple fund generations referenced (Fund I, II, III). Portfolio shows investment activity across Business Services, Industrials, Tech/Media/Telecom, and Financial Services. HQ in New York with secondary office in West Palm Beach. Specific sizing metrics, AUM, and deal check sizes not disclosed on provided pages. | AC68: =COUNTIF(Sheet1!$A$1:$A$50,Firms!A68) -> 0
A69: Brixey & Meyer Capital LLC | B69: PE | C69: Ohio | D69: Cincinnati | E69: https://www.bmcgrowth.com | F69: primarily | I69: 2.0 | J69: 10.0 | O69: Buyout | P69: Industrials, Business Services, Healthcare | T69: 201.81 | U69: Active | X69: High | Y69: No | Z69: 2026-06-07 | AA69: complete | AB69: Seeded from CapIQ export. Numeric fields are regex first-pass — crawler will confirm. capiq_description preserved for AI extraction fallback. | [extractor] Investment criteria explicitly stated on website: EBITDA $2-10M, industry niches with growth opportunities, strong management teams required, geographic focus on Eastern and Central time zones (portfolio heavily concentrated in Ohio, Tennessee, Michigan, Indiana). Firm type classified as PE based on control acquisitions and buyout strategy. Portfolio shows active deal flow. No fund-level data (AUM, vintage, fund name) available on website. | AC69: =COUNTIF(Sheet1!$A$1:$A$50,Firms!A69) -> 0
A70: Broadtree Partners, LLC | B70: PE | C70: NC | D70: Charlotte | E70: https://broadtreepartners.com | F70: true | I70: 3.0 | O70: Buyout, Growth Equity | P70: Generalist | U70: Active | X70: Medium | Y70: No | Z70: 2026-06-05 | AA70: complete | AB70: Seeded from CapIQ export. Numeric fields are regex first-pass — crawler will confirm. capiq_description preserved for AI extraction fallback. | [extractor] Broadtree Partners is a lower middle-market PE firm in Charlotte, NC. Investment criteria confirmed: EBITDA min ~$3M (stated as $3M floor with margins noted), majority investments, privately held US-based companies with history of profitability and EBITDA growth. Page references '10' next to EBITDA growth history and '75' next to revenues but context is unclear — possibly $75M revenue max or EBITDA as % of revenues; figures not definitively interpretable. No fund name, AUM, or deal dates confirmed. Sector focus appears generalist. 25+ portfolio companies noted. | AC70: =COUNTIF(Sheet1!$A$1:$A$50,Firms!A70) -> 0
A71: Broadwater Capital Partners, LLC | B71: PE | C71: ND | D71: Fargo | E71: https://www.bwcap.com | F71: primarily | G71: 20.0 | H71: 100.0 | I71: 2.0 | J71: 10.0 | O71: Buyout, Minority | P71: Industrials, Business Services, Consumer | U71: Active | X71: High | Y71: No | Z71: 2026-06-07 | AA71: complete | AB71: Seeded from CapIQ export. Numeric fields are regex first-pass — crawler will confirm. capiq_description preserved for AI extraction fallback. | [extractor] Broadwater Capital established 2021 in Fargo, ND. Invests in lower middle market companies in greater Midwest (13-state region). Prefers majority control but maintains flexibility for minority stakes. No fund-specific AUM or check size data disclosed on website. Explicit target industries: agribusiness, business services, consumer, distribution, light industrials, manufacturing, technology. | AC71: =COUNTIF(Sheet1!$A$1:$A$50,Firms!A71) -> 0
A72: Broadwing Capital Management, LLC | B72: PE | E72: https://www.broadwingcap.com | F72: primarily | I72: 5.0 | O72: Buyout, Growth Equity | P72: Industrials, Business Services | T72: 513.11 | U72: Active | X72: High | Y72: No | Z72: 2026-06-07 | AA72: complete | AB72: Seeded from CapIQ export. Numeric fields are regex first-pass — crawler will confirm. capiq_description preserved for AI extraction fallback. | [extractor] Investment criteria explicitly stated on site. EBITDA range is $5-25M+ (min 5.0, max open-ended — 25M noted as floor for '+' range, set ebitda_max to null). Focus on control equity investments (limited structured equity/debt) in North American headquartered companies; founder/family/entrepreneur sellers preferred. Deal types include buy-and-build, complex situations, and management buyouts. Geography is North America broadly, not US-only. HQ city/state not listed on site. AUM and fund details not disclosed. | AC72: =COUNTIF(Sheet1!$A$1:$A$50,Firms!A72) -> 0
A73: Brodie Generational Capital Partners, LLC | B73: Family Office | C73: PA | D73: Radnor | E73: https://bgencap.com | F73: primarily | G73: 100.0 | I73: 20.0 | J73: 50.0 | K73: 150.0 | L73: 500.0 | O73: Buyout | P73: Industrials, Healthcare | S73: consumer, b2c | X73: High | Y73: No | Z73: 2026-06-07 | AA73: complete | AB73: Seeded from CapIQ export. Numeric fields are regex first-pass — crawler will confirm. capiq_description preserved for AI extraction fallback. | [extractor] Family-owned investment firm investing own capital. Focuses on control acquisitions (buyout) of established middle-market businesses in industrial/manufacturing sectors. Explicit criteria: US or UK HQ, revenue $100M+, EBITDA $20-50M, deal size $150-500M, B2B distribution, family-owned preference, control position required. Portfolio includes Sur-Seal and Zahav Bioscience. No fund structure identified; appears to be evergreen family office vehicle. | AC73: =COUNTIF(Sheet1!$A$1:$A$50,Firms!A73) -> 1 | AD73: =SUBSTITUTE(AB73,"Seeded from CapIQ export. Numeric fields are regex first-pass — c","C") -> Crawler will confirm. capiq_description preserved for AI extraction fallback. | [extractor] Family-owned investment firm investing own capital. Focuses on control acquisitions (buyout) of established middle-market businesses in industrial/manufacturing sectors. Explicit criteria: US or UK HQ, revenue $100M+, EBITDA $20-50M, deal size $150-500M, B2B distribution, family-owned preference, control position required. Portfolio includes Sur-Seal and Zahav Bioscience. No fund structure identified; appears to be evergreen family office vehicle.
A74: Brookfield Asset Management Ltd. (TSX:BAM) | B74: Other | D74: New York | E74: https://www.bam.brookfield.com | F74: true | P74: Infrastructure, Real Estate, Energy | T74: 1000000.0 | U74: Active | X74: Low | Y74: No | Z74: 2026-06-07 | AA74: complete | AB74: Seeded from CapIQ export. Numeric fields are regex first-pass — crawler will confirm. capiq_description preserved for AI extraction fallback. | [extractor] Brookfield Asset Management is a global alternative asset manager headquartered in New York with $1T+ AUM. Firm type classified as 'Other' as it is a multi-strategy asset manager rather than traditional PE/VC. Primary sectors mentioned: infrastructure, energy, private equity, real estate, and credit. 250K+ operating employees. Recent major deals noted (Oaktree acquisition, Qatar AI venture). Confidence Medium: firm scope and AUM confirmed, but specific investment criteria (check sizes, revenue/EBITDA targets, deal types) not explicitly stated on homepage. Needs review due to complexity of multi-strategy platform and lack of explicit investment criteria details. | AC74: =COUNTIF(Sheet1!$A$1:$A$50,Firms!A74) -> 0
A75: Brydon Group, LLC | B75: PE | C75: DC | D75: Washington | E75: https://www.brydon.com | F75: true | G75: 5.0 | H75: 25.0 | I75: 1.0 | J75: 5.0 | O75: Buyout | P75: Business Services, Healthcare, Technology | T75: 570.0 | U75: Active | X75: High | Y75: No | Z75: 2026-06-07 | AA75: complete | AB75: Seeded from CapIQ export. Numeric fields are regex first-pass — crawler will confirm. capiq_description preserved for AI extraction fallback. | [extractor] Criteria explicitly stated on approach page: $5-25M revenue, $1-5M EBITDA, target 90-100% buyout, high recurring revenue, low capex, low customer concentration. Focus sectors: Business Services, Healthcare Services, Government Services, Software. AUM of $570M+ as of 12/31/2025. 46 acquisitions as of 3/10/2026, 21 CEOs operating since 2022. Launches ~6 platforms per year. HQ at 2000 Pennsylvania Ave Suite 5004, Washington D.C. 20006. CEO-in-Residence program is a key talent/deal sourcing mechanism. No check size or EV range explicitly stated. | AC75: =COUNTIF(Sheet1!$A$1:$A$50,Firms!A75) -> 0
A76: Burton Hill Capital | B76: Other | E76: https://www.burtonhillcapital.com | O76: Buyout | P76: Generalist | U76: Active | X76: Medium | Y76: No | Z76: 2026-06-07 | AA76: complete | AB76: Seeded from CapIQ export. Numeric fields are regex first-pass — crawler will confirm. capiq_description preserved for AI extraction fallback. | [extractor] Firm explicitly states focus on acquiring and operating small-to-medium businesses for long-term hold, not typical PE/VC model. Describes self as different from private equity. Privately held investment firm with committed private capital. No geographic location, AUM, or specific deal size parameters confirmed. One-pager PDF referenced but not parsed: https://dl.dropboxusercontent.com/u/18432039/Burton%20Hill%20One%20Pager.pdf. Needs review: firm classification ambiguous—could be Fundless Sponsor, Search Fund, or Family Office; insufficient data on HQ location and specific investment criteria. | AC76: =COUNTIF(Sheet1!$A$1:$A$50,Firms!A76) -> 0
A77: Butterfly Equity, LP | B77: PE | C77: CA | D77: Beverly Hills | E77: https://www.bfly.com | F77: Yes | P77: Industrials, Consumer, Technology | T77: 7084.56 | U77: Active | X77: Low | Y77: Yes | Z77: 2026-06-07 | AA77: complete | AB77: Seeded from CapIQ export. Numeric fields are regex first-pass — crawler will confirm. capiq_description preserved for AI extraction fallback. | [extractor] Confirmed: Beverly Hills, CA HQ (9595 Wilshire Blvd, Suite 510). Firm type PE inferred from name and portfolio activity. Page shows active/realized investments tracked but no investment criteria, sector focus, ticket sizes, or fund details provided in source material. Significant data gaps require review of additional sources. | AC77: =COUNTIF(Sheet1!$A$1:$A$50,Firms!A77) -> 0
A78: CCMP Growth Advisors, LP | B78: PE | E78: https://www.ccmpgrowth.com | F78: primarily | M78: 50.0 | N78: 200.0 | O78: Buyout, Growth Equity | P78: Consumer, Industrials, Business Services | Q78: Smart Automation Technologies, Resilient Tech-Enabled Services, Essential & Experiential Consumer Services, B2B2C Value Chain Outsourcing & Distribution, Consumer Nutrition, Health & Wellness, Home Automation & Enthusiast Products | R78: Energy efficiency & management, Factory & warehouse automation, Automated testing & monitoring technology, Engineered components, Outsourced facility & business services, Utility, environmental & infrastructure services, Professional & skilled technical services, Supply chain services, Continuing professional education, Home & residential services, Travel & leisure services, Restaurants & experiential multi-channel retail, Consumer convenience & education services, Outsourced innovation and manufacturing services, Specialty distribution, Private label and trade brands, Vitamins and healthier for you products, Health & fitness services & products, Personal care & beauty, Facility-based consumer healthcare & childcare, Engineered consumer products, Home automation technologies, Auto aftermarket products & services, Pet, home & outdoor living products | T78: 818.53 | U78: Active | X78: High | Y78: No | Z78: 2026-06-07 | AA78: complete | AB78: Seeded from CapIQ export. Numeric fields are regex first-pass — crawler will confirm. capiq_description preserved for AI extraction fallback. | [extractor] Investment criteria explicitly stated on website. Check size $50-200M including LP coinvest. Focus on North American privately-held consumer, industrial tech, and services businesses. Predominantly control buyouts with selective growth equity. Target companies with 10%+ organic growth. Focus on family-owned, founder-led, and middle market platforms in transition. HQ city/state not confirmed from source pages. AUM not disclosed. Firm overview PDF found: https://www.ccmpgrowth.com/images/home/CCMPGrowth-FirmOverview-Q12026.pdf — not parsed. References legacy funds CCMP II, CCMP III, and CCMP III CV. | AC78: =COUNTIF(Sheet1!$A$1:$A$50,Firms!A78) -> 0
A79: CORE Industrial Partners, LLC | B79: PE | E79: https://www.coreipfund.com | F79: true | O79: Buyout | P79: Industrials | U79: Active | X79: Medium | Y79: No | Z79: 2026-06-07 | AA79: complete | AB79: Seeded from CapIQ export. Numeric fields are regex first-pass — crawler will confirm. capiq_description preserved for AI extraction fallback. | [extractor] Portfolio page confirms PE focus on manufacturing, industrial technology & services with buyout strategy. Firm name and sector focus confirmed via schema markup. HQ location, fund details, AUM, check sizes, and specific investment criteria not found on provided page content. Page last modified 2025-08-21. Needs review to confirm HQ location and obtain additional fund/investment criteria details from other sources. | AC79: =COUNTIF(Sheet1!$A$1:$A$50,Firms!A79) -> 0
A80: CVC Capital Partners plc (ENXTAM:CVC) | B80: PE | E80: https://www.cvc.com | F80: true | O80: Buyout | P80: Technology, Healthcare, Industrials | T80: 228571.4 | U80: Active | X80: Medium | Y80: No | Z80: 2026-06-07 | AA80: complete | AB80: Seeded from CapIQ export. Numeric fields are regex first-pass — crawler will confirm. capiq_description preserved for AI extraction fallback. | [extractor] CVC Capital Partners is a global PE firm with €209 billion AUM (~$228.6B USD as of March 2026). Portfolio includes 150+ companies across multiple strategies (Europe/Americas, Asia, Strategic Opportunities, Catalyst, Secondaries, Credit, Infrastructure). Confirmed sectors: Technology, Healthcare, Industrials, Financial Services, Consumer/Retail, Distribution, Energy, Manufacturing, Chemicals, Business Services, Sports/Media, Transportation/Infrastructure, Utilities, Building/Construction. HQ location not explicitly stated in source material. | AC80: =COUNTIF(Sheet1!$A$1:$A$50,Firms!A80) -> 1 | AD80: =SUBSTITUTE(AB80,"Seeded from CapIQ export. Numeric fields are regex first-pass — c","C") -> Crawler will confirm. capiq_description preserved for AI extraction fallback. | [extractor] CVC Capital Partners is a global PE firm with €209 billion AUM (~$228.6B USD as of March 2026). Portfolio includes 150+ companies across multiple strategies (Europe/Americas, Asia, Strategic Opportunities, Catalyst, Secondaries, Credit, Infrastructure). Confirmed sectors: Technology, Healthcare, Industrials, Financial Services, Consumer/Retail, Distribution, Energy, Manufacturing, Chemicals, Business Services, Sports/Media, Transportation/Infrastructure, Utilities, Building/Construction. HQ location not explicitly stated in source material.
A81: CX Institutional, LLC | B81: Other | E81: https://credentwealth.com | F81: true | T81: 4464.69 | X81: Low | Y81: Yes | Z81: 2026-06-05 | AA81: complete | AB81: Seeded from CapIQ export. Numeric fields are regex first-pass — crawler will confirm. capiq_description preserved for AI extraction fallback. | [extractor] CX Institutional, LLC is mentioned only as a registered investment advisor affiliated with Credent Wealth Management, a retail wealth management/financial planning firm. The source page contains no PE/VC investment criteria — no deal types, sector focus, check sizes, or portfolio company data. This entity does not appear to be a PE/VC firm. Needs review to confirm correct firm was intended for this database. | AC81: =COUNTIF(Sheet1!$A$1:$A$50,Firms!A81) -> 0
A82: Calera Capital Advisors, LP | B82: PE | C82: MA | D82: Boston | E82: https://www.caleracapital.com | F82: true | O82: Buyout | P82: Business Services, Industrials | U82: Active | V82: 2024-12-31 | X82: Medium | Y82: No | Z82: 2026-06-07 | AA82: complete | AB82: Seeded from CapIQ export. Numeric fields are regex first-pass — crawler will confirm. capiq_description preserved for AI extraction fallback. | [extractor] Calera Capital is a PE firm with HQ in Boston and secondary office in San Francisco. Three sector focus areas explicitly stated: Business Services, Logistics, and Specialty Industrials. Invests in mid-market control acquisitions with value-creation through operational improvements and organic growth rather than leverage. Multiple active portfolio companies as of 12/31/2024. Fund names mentioned (Fund VI, Fund V, Calera Image Holdings) but vintage years and AUM not disclosed on pages reviewed. Confidence is Medium due to lack of explicit deal sizing, fund vintage, and AUM data. Needs review because page shows placeholder values ('0 Years in Business', '0 Funds Created', '0 Assets Under Management') suggesting incomplete data on website. | AC82: =COUNTIF(Sheet1!$A$1:$A$50,Firms!A82) -> 0
A83: Capitol Meridian Partners LP | B83: PE | C83: DC | D83: Washington | E83: https://www.capitolmeridian.com | F83: primarily | I83: 5.0 | M83: 50.0 | O83: Buyout, Growth Equity, Other | P83: Technology, Industrials, Business Services | T83: 1669.26 | U83: Active | X83: High | Y83: No | Z83: 2026-06-07 | AA83: complete | AB83: Seeded from CapIQ export. Numeric fields are regex first-pass — crawler will confirm. capiq_description preserved for AI extraction fallback. | [extractor] Investment criteria explicitly stated on target sectors page. EBITDA range: $5M-$75M+ for new platform investments. Equity checks: $50M-$250M+ upfront or over time. Transaction types: control-oriented buyout, growth, and carve-out. Geography: North America. EBITDA max of 75M+ and check size max of 250M+ noted as open-ended minimums. Portfolio includes Altumint (state/local software), Clarity (national security), LMI (federal gov services), Parry Labs (defense tech), PrimeFlight (aviation), Launch (commercial aviation), Beaufort (defense products), TechnoMile (gov contracting software). No fund name, vintage year, or AUM data found on site. | AC83: =COUNTIF(Sheet1!$A$1:$A$50,Firms!A83) -> 0
A84: Carbyne Equity Partners | B84: PE | D84: Hamburg | E84: https://www.carbynepartners.de | F84: false | N84: 150.0 | O84: Buyout, Growth Equity | P84: Healthcare, Industrials, Business Services | T84: 130.0 | U84: Active | V84: 2025 | X84: Medium | Y84: No | Z84: 2026-06-07 | AA84: complete | AB84: Seeded from CapIQ export. Numeric fields are regex first-pass — crawler will confirm. capiq_description preserved for AI extraction fallback. | [extractor] Carbyne Equity Partners is a German PE firm founded in 2023, backed by single German family LP. Focus on European buyouts and growth equity in Healthcare (MedTech, Life Science Services, Biotech), Nutrition & Ingredients, and Agricultural Inputs. Buyout check size up to €150m; Growth Equity up to €50m (converted to USD equivalent: 150.0 and 50.0). Geography: platform investments in Europe, add-ons worldwide. Multiple deals closed in 2025 (SuanNutra in Spain, Chemia in Italy). Majority stakes preferred for buyouts; both majority and minority stakes for growth equity. Minimum profitability required; no turnarounds. Single-LP structure enables operational flexibility. | AC84: =COUNTIF(Sheet1!$A$1:$A$50,Firms!A84) -> 0
A85: Carolwood L.P. | B85: PE | E85: https://www.carolwoodlp.com | F85: primarily | P85: Industrials, Technology | U85: Active | X85: Low | Y85: Yes | Z85: 2026-06-04 | AA85: complete | AB85: Seeded from CapIQ export. Numeric fields are regex first-pass — crawler will confirm. capiq_description preserved for AI extraction fallback. | [crawler] Thin website — minimal investment criteria found. Manual review recommended. | AC85: =COUNTIF(Sheet1!$A$1:$A$50,Firms!A85) -> 0
A86: Catchment Capital, L.P. | B86: PE | E86: https://www.catchmentcapital.com | F86: primarily | J86: 75.0 | O86: Buyout | P86: Industrials | U86: Active | X86: Medium | Y86: No | Z86: 2026-06-07 | AA86: complete | AB86: Seeded from CapIQ export. Numeric fields are regex first-pass — crawler will confirm. capiq_description preserved for AI extraction fallback. | [extractor] PE firm focused on middle-market industrial companies in North America and Western Europe. Invests up to $75M EBITDA. Strategy emphasizes transformational growth initiatives through proprietary CaST process. Language suggests buyout/control model with strategic value-add. HQ location not provided on website. No fund-specific details (name, vintage, AUM) disclosed. Confidence Medium due to lack of explicit deal size, geographic HQ, and fund details. Needs review for potential fund documentation or additional sources. | AC86: =COUNTIF(Sheet1!$A$1:$A$50,Firms!A86) -> 0
A87: Cedar Springs Advisors, LLC | B87: Other | C87: TX | D87: Dallas | E87: https://www.cedarspringscapital.com | F87: true | O87: Minority | P87: Generalist | T87: 220.66 | U87: Active | X87: Medium | Y87: No | Z87: 2026-06-07 | AA87: complete | AB87: Seeded from CapIQ export. Numeric fields are regex first-pass — crawler will confirm. capiq_description preserved for AI extraction fallback. | [extractor] Cedar Springs Capital/Advisors operates as SEC-registered investment adviser focused on secondary transactions (GP-led secondaries, secondary directs) and minority/co-investments in middle-market and lower middle-market companies. Firm type unclear—appears to be specialized secondary/minority investor, classified as 'Other'. Deal strategy emphasizes secondaries and minority stakes; no explicit buyout/control language. No AUM, fund vintage, check size, or sector focus details provided. Activity appears active based on current website. Confidence medium due to limited explicit criteria; needs review for firm classification and deal type confirmation. | AC87: =COUNTIF(Sheet1!$A$1:$A$50,Firms!A87) -> 0
A88: Center Rock Capital Partners, LP | B88: PE | E88: https://www.centerrockcp.com | F88: true | O88: Buyout | P88: Industrials | T88: 1734.53 | U88: Active | X88: Medium | Y88: No | Z88: 2026-06-07 | AA88: complete | AB88: Seeded from CapIQ export. Numeric fields are regex first-pass — crawler will confirm. capiq_description preserved for AI extraction fallback. | [extractor] PE firm focused on industrial businesses. Confirmed buyout deal type and industrials sector based on homepage language ('leading industrial businesses', 'industrial franchises'). Portfolio includes 10 companies with recent exit (Wolverine, Diamond-C in 2025). HQ location not stated on homepage. Fact sheet PDF available: https://www.centerrockcp.com/wp-content/uploads/2023/09/CRCP-Fact-Sheet-as-of-Q1-2026.pdf — not parsed. Investment criteria page exists but content not provided. Needs_review=true due to missing HQ location, fund details, and specific financial criteria. | AC88: =COUNTIF(Sheet1!$A$1:$A$50,Firms!A88) -> 0
A89: CenterGate Capital, L.P. | B89: PE | E89: https://www.centergatecapital.com | F89: primarily | I89: 5.0 | J89: 30.0 | O89: Buyout | P89: Business Services, Industrials, Consumer | T89: 750.0 | U89: Active | X89: High | Y89: No | Z89: 2026-06-07 | AA89: complete | AB89: Seeded from CapIQ export. Numeric fields are regex first-pass — crawler will confirm. capiq_description preserved for AI extraction fallback. | [extractor] PE firm managing $750M AUM. Explicit investment criteria: $5-30M EBITDA platform size in Business Services, Manufacturing, and Consumer sectors. Portfolio shows diverse buyout activity across North America (primarily US & Canada). One Page Overview PDF available at https://www.centergatecapital.com/_files/ugd/63f745_9a5cc5add04d4942bfaf939b87d07e4c.pdf — not parsed. HQ city/state not explicitly stated on pages provided. | AC89: =COUNTIF(Sheet1!$A$1:$A$50,Firms!A89) -> 0
A90: CenterOak Partners LLC | B90: Other | E90: https://centeroakpartners.com | P90: Energy, Industrials, Healthcare | T90: 1110.0 | U90: Active | X90: Low | Y90: Yes | Z90: 2026-06-07 | AA90: complete | AB90: Seeded from CapIQ export. Numeric fields are regex first-pass — crawler will confirm. capiq_description preserved for AI extraction fallback. | [extractor] Page content appears to be CSS/HTML boilerplate only with no substantive investment criteria data. Strategy page URL provided but no actual strategy information extracted. Requires visit to actual website content or additional source pages to confirm firm details. | AC90: =COUNTIF(Sheet1!$A$1:$A$50,Firms!A90) -> 0
A91: Centerbridge Partners, L.P. | B91: PE | E91: https://www.centerbridge.com | O91: Buyout | P91: Generalist | U91: Active | X91: Medium | Y91: No | Z91: 2026-06-07 | AA91: complete | AB91: Seeded from CapIQ export. Numeric fields are regex first-pass — crawler will confirm. capiq_description preserved for AI extraction fallback. | [extractor] Centerbridge Partners founded 2005, operates PE, Credit, and Real Estate strategies. PE platform launched 2006. Firm description indicates control-oriented, multi-strategy approach with focus on downside protection and intrinsic value. No specific investment criteria, check sizes, AUM, sector focus, or deal count data found on pages reviewed. Headquarters location not specified. Needs review due to lack of specific investment criteria details. | AC91: =COUNTIF(Sheet1!$A$1:$A$50,Firms!A91) -> 0
A92: Centre Partners Management LLC | B92: PE | C92: NY | D92: New York | E92: https://www.centrepartners.com | F92: primarily | O92: Buyout | P92: Consumer, Healthcare | T92: 2700.0 | U92: Active | X92: Medium | Y92: No | Z92: 2026-06-07 | AA92: complete | AB92: Seeded from CapIQ export. Numeric fields are regex first-pass — crawler will confirm. capiq_description preserved for AI extraction fallback. | [extractor] Centre Partners is a PE firm focused on control investments in North American middle-market businesses. Primary sectors: Consumer Products & Services and Healthcare Services. 38+ year track record with $2.7B capital invested, 91 platform companies, 175+ add-on acquisitions. Headquarters in New York with office in Los Angeles. Specializes in entrepreneur, founder, and family-owned business acquisitions with transition/succession planning solutions. | AC92: =COUNTIF(Sheet1!$A$1:$A$50,Firms!A92) -> 0
A93: Cerberus Capital Management, L.P. | B93: PE | E93: https://www.cerberus.com | F93: true | O93: Buyout | P93: Industrials, Consumer, Business Services | T93: 85771.29 | U93: Active | X93: Medium | Y93: Yes | Z93: 2026-06-07 | AA93: complete | AB93: Seeded from CapIQ export. Numeric fields are regex first-pass — crawler will confirm. capiq_description preserved for AI extraction fallback. | [extractor] Cerberus Capital Management confirmed as PE firm with portfolio of 19 companies and 655 active job postings. One portfolio company identified: Closure Systems International (CSI), packaging/manufacturing founded 1972, with US operations. No explicit investment criteria, fund details, AUM, or HQ location found on provided pages. Firm type inferred as PE based on portfolio company structure and buyout activity. Additional research needed for comprehensive investment criteria. | AC93: =COUNTIF(Sheet1!$A$1:$A$50,Firms!A93) -> 0
A94: Certares Management LLC | B94: PE | C94: NY | D94: New York | E94: https://www.certares.com | P94: Consumer, Business Services | U94: Active | X94: Low | Y94: Yes | Z94: 2026-06-07 | AA94: complete | AB94: Seeded from CapIQ export. Numeric fields are regex first-pass — crawler will confirm. capiq_description preserved for AI extraction fallback. | [extractor] Founded in 2012. Focus on travel and tourism, hospitality, business and consumer services. No deal size, check size, fund, or AUM data found in source pages. Strategies page (https://certares.com/strategies/) was listed in nav but content was not fully parsed — may contain additional investment criteria. No PDF criteria documents found. | AC94: =COUNTIF(Sheet1!$A$1:$A$50,Firms!A94) -> 0
A95: Chapter One Ventures, LLC | B95: VC | C95: CA | D95: San Francisco | E95: https://chapterone.com | F95: primarily | O95: Venture | P95: Technology | U95: Active | V95: 2024 | X95: Medium | Y95: No | Z95: 2026-06-07 | AA95: complete | AB95: Seeded from CapIQ export. Numeric fields are regex first-pass — crawler will confirm. capiq_description preserved for AI extraction fallback. | [extractor] VC firm investing in early-stage technology startups. Portfolio categories visible: AI/ML, Consumer, Crypto, Defense, Dev Tools, Fintech, Physical World, SaaS. Team includes Jeff Morris Jr. and Jamesin Seidel. Recent investments in Ragie (Aug 2024) and Hyperbolic (July 2024) noted. Hiring SF-based investment partner (July 2025). No explicit fund size, vintage year, check size, or stage criteria found on provided pages. HQ inferred as San Francisco based on SF hiring and portfolio focus; needs_review=true due to lack of explicit criteria confirmation. | AC95: =COUNTIF(Sheet1!$A$1:$A$50,Firms!A95) -> 0
A96: Charger Investment Partners LP | B96: PE | E96: https://www.chargerinv.com | F96: primarily | G96: 25.0 | H96: 350.0 | J96: 35.0 | M96: 15.0 | N96: 100.0 | O96: Buyout, Recap | P96: Industrials, Consumer, Business Services | T96: 865.31 | U96: Active | X96: High | Y96: No | Z96: 2026-06-07 | AA96: complete | AB96: Seeded from CapIQ export. Numeric fields are regex first-pass — crawler will confirm. capiq_description preserved for AI extraction fallback. | [extractor] Explicit investment criteria found on approach page. Invests in middle market through recaps, divestitures, MBOs, and private sales. Prefers control but considers significant minority stakes. Geography: US or Canada headquarters. Portfolio demonstrates active investment across industrials, consumer, and business services sectors. No fund-specific details (name, vintage, AUM) disclosed on public site. | AC96: =COUNTIF(Sheet1!$A$1:$A$50,Firms!A96) -> 0
A97: Chaver Capital Partners | B97: PE | E97: https://www.chavercap.com | F97: true | O97: Buyout | P97: Consumer | U97: Active | X97: Medium | Y97: No | Z97: 2026-06-07 | AA97: complete | AB97: Seeded from CapIQ export. Numeric fields are regex first-pass — crawler will confirm. capiq_description preserved for AI extraction fallback. | [extractor] Operator-driven PE firm targeting lower middle market businesses in the US. Portfolio includes consumer-facing companies (frozen desserts, staffing, gum, food distribution, home décor). No explicit financial criteria, fund details, or HQ location provided on website. Inferred PE/Buyout based on 'operator-driven' language and control-oriented portfolio. Confidence limited by lack of explicit investment criteria documentation. | AC97: =COUNTIF(Sheet1!$A$1:$A$50,Firms!A97) -> 0
A98: Chimney Rock Equity Partners, LLC | B98: PE | C98: TX | D98: Austin | E98: https://www.chimneyrockequity.com | F98: primarily | I98: 5.0 | J98: 20.0 | L98: 250.0 | O98: Buyout | P98: Industrials | U98: Active | X98: High | Y98: No | Z98: 2026-06-07 | AA98: complete | AB98: Seeded from CapIQ export. Numeric fields are regex first-pass — crawler will confirm. capiq_description preserved for AI extraction fallback. | [extractor] PE firm focused on industrials sector with explicit investment criteria. Target platform investments: $5-20M EBITDA, transaction values up to $250M, control transactions, North America HQ, conservative capital structures. Three focus areas: Aerospace & Defense, Industrial Products & Services, Niche Products & Services. Low disruption risk, large installed base, consumables, high visibility, diversified customer base, barriers to entry emphasized. Control acquisitions with repeatable value creation strategy. | AC98: =COUNTIF(Sheet1!$A$1:$A$50,Firms!A98) -> 1 | AD98: =SUBSTITUTE(AB98,"Seeded from CapIQ export. Numeric fields are regex first-pass — c","C") -> Crawler will confirm. capiq_description preserved for AI extraction fallback. | [extractor] PE firm focused on industrials sector with explicit investment criteria. Target platform investments: $5-20M EBITDA, transaction values up to $250M, control transactions, North America HQ, conservative capital structures. Three focus areas: Aerospace & Defense, Industrial Products & Services, Niche Products & Services. Low disruption risk, large installed base, consumables, high visibility, diversified customer base, barriers to entry emphasized. Control acquisitions with repeatable value creation strategy.
A99: Citation Capital Management, LLC | B99: PE | C99: TX | D99: Dallas | E99: https://www.citation.capital | F99: true | O99: Buyout, Growth Equity, Minority | P99: Generalist | T99: 1359.92 | U99: Active | X99: Low | Y99: Yes | Z99: 2026-06-07 | AA99: complete | AB99: Seeded from CapIQ export. Numeric fields are regex first-pass — crawler will confirm. capiq_description preserved for AI extraction fallback. | [extractor] Citation Capital Management is a Dallas-based PE firm focused exclusively on family- and founder-owned businesses. Investment strategy includes control buyouts, minority investments, and structured equity. Team background includes BDT Capital, Goldman Sachs Merchant Bank, and CPPIB. No explicit investment criteria (check size, revenue/EBITDA thresholds, target sectors, or fund details) were found on the site. HQ appears to be Dallas, TX based on founder/team references, though some staff are based in New York and Connecticut. Activity tier set to Active based on staffing depth. Confidence is Low due to absence of explicit investment criteria. No criteria PDF found. | AC99: =COUNTIF(Sheet1!$A$1:$A$50,Firms!A99) -> 0
A100: Clayton, Dubilier & Rice, LLC | B100: PE | E100: https://www.cdr.com | F100: primarily | O100: Buyout | P100: Healthcare, Industrials, Technology | Q100: Consumer, Financial Services | U100: Active | V100: 2024 | X100: Medium | Y100: No | Z100: 2026-06-07 | AA100: complete | AB100: Seeded from CapIQ export. Numeric fields are regex first-pass — crawler will confirm. capiq_description preserved for AI extraction fallback. | [extractor] CD&R is a control-oriented PE firm focused solely on private equity with a single fund structure. Invests in North America and Europe across Healthcare, Consumer & Retail Services, Financial Services, Industrials & Business Services, and Technology. Recent deal: R1 RCM acquisition (2024, $8.9B enterprise value, co-invested with TowerBrook). Partnership-oriented approach with operational value-add focus. HQ location not specified in provided content. | AC100: =COUNTIF(Sheet1!$A$1:$A$50,Firms!A100) -> 0
...

Sheet Sheet2
A1: Firm Name | B1: Type | C1: State | D1: City | E1: Website | F1: US Investments | G1: Revenue Min ($M) | H1: Revenue Max ($M) | I1: EBITDA Min ($M) | J1: EBITDA Max ($M) | K1: EV Min ($M) | L1: EV Max ($M) | M1: Check Min ($M) | N1: Check Max ($M) | O1: Deal Types | P1: Sector Tier 1 | Q1: AUM ($M) | R1: Activity | S1: Last Deal | T1: Fund Name | U1: Confidence | V1: Needs Review | W1: Last Checked | X1: Status | Y1: Notes
A2: A&M Capital Advisors, LP | B2: PE | C2: CT | D2: Greenwich | E2: https://www.a-mcapital.com | F2: primarily | I2: 15.0 | J2: 100.0 | K2: 75.0 | L2: 750.0 | M2: 25.0 | N2: 200.0 | O2: Buyout, Recap, Other | P2: Business Services, Healthcare, Industrials | Q2: 5900.0 | R2: Active | U2: High | V2: No | W2: 2026-06-07 | X2: complete | Y2: Crawler will confirm. capiq_description preserved for AI extraction fallback. | [extractor] Multi-strategy PE firm with 4 distinct investment strategies (AMCP, AMCS, AMCE, AMCSI). Data extracted from primary investment criteria sections. AMCP flagship strategy: $3.0B AUM, $60-200M check size, $150-750M target EV, $20-100M EBITDA. AMCS secondaries: $25-75M initial checks, $100-500M EV, $15M+ underlying EBITDA. AMCE (Europe): €650M AUM (~$710M USD). AMCSI: $10-50M checks, $100M+ EV, $20M+ EBITDA. Total firm AUM stated as $5.9B. Transaction types include founder transitions, build-ups, corporate divestitures, public-to-privates, and special situations. Active investor with 170+ companies invested across 24 platforms since inception.
A3: AE Industrial Partners, LP | B3: PE | C3: FL | D3: Boca Raton | E3: https://www.aeroequity.com | F3: true | O3: Buyout, Minority | P3: Industrials, Technology | R3: Active | S3: 2025-06-01 | U3: Medium | V3: No | W3: 2026-06-07 | X3: complete | Y3: Crawler will confirm. capiq_description preserved for AI extraction fallback. | [extractor] AE Industrial Partners is a PE firm focused on aerospace, national security, and industrial services. Founded 2015. 30+ platform companies and 80+ minority/add-on investments completed. Two PDFs available but not parsed: 2025 Year In Review (https://www.aeroequity.com/wp-content/uploads/AE-Industrial-Partners-2025-Year-In-Review.pdf) and Fact Sheet April 2026 (https://www.aeroequity.com/wp-content/uploads/AE-Industrial-Fact-Sheet-April-2026.pdf). Also operates AE Ventures (early-stage tech) and AEI Aerospace Leasing. Additional office in Washington, D.C.
A4: Agellus Capital, LLC | B4: PE | E4: https://www.agellus.com | F4: true | I4: 2.0 | J4: 25.0 | O4: Buyout | P4: Business Services, Consumer, Industrials | Q4: 400.0 | R4: Active | S4: 2026-03-01 | T4: Fund I | U4: High | V4: No | W4: 2026-06-07 | X4: complete | Y4: Crawler will confirm. capiq_description preserved for AI extraction fallback. | [extractor] PE firm focused on essential, non-discretionary services. Platform target: $2-25M EBITDA; add-ons any size. Buy-and-build strategy with focus on fragmented markets. Three key verticals: B2B Services, Non-Discretionary Consumer Services, Supply Chain & Infrastructure. Recent investments: Bluejack (Dec 2024), CompassMSP (Sept 2024), HighGrove (Nov 2025), Titan Restoration (Mar 2026). HQ location not explicitly stated on pages provided. Tearsheet PDF available: https://www.agellus.com/documents/FG/agellus/about/652199_Agellus_Tearsheet_-_Feb_2026_1.pdf
A5: Align Capital Partners, LP | B5: PE | C5: TX | D5: Dallas | E5: https://www.aligncp.com | F5: primarily | I5: 3.0 | J5: 15.0 | L5: 150.0 | M5: 20.0 | N5: 60.0 | O5: Buyout | P5: Technology, Business Services, Industrials | Q5: 2100.0 | R5: Active | S5: 2026-05-28 | U5: High | V5: No | W5: 2026-06-07 | X5: complete | Y5: Crawler will confirm. capiq_description preserved for AI extraction fallback. | [extractor] Control-focused PE firm with offices in Cleveland and Dallas. Explicitly targets lower-middle market companies with 3-15mm EBITDA (or >5mm ARR for software). Check sizes 20-60mm hold value. Core criteria: actionable organic growth, recurring revenue, niche leadership, 30%+ gross margins, 15%+ EBITDA margins. North America focus (primarily US). Recent deals through May 2026. PDF overview available at https://aligncp.com/wp-content/uploads/ACP-Firm-Overview.pdf
A6: Amberjack Capital Partners, L.P. | B6: PE | C6: Texas | D6: Houston | E6: https://www.amberjackcapital.com | F6: true | I6: 4.0 | J6: 20.0 | K6: 20.0 | L6: 175.0 | M6: 20.0 | N6: 75.0 | O6: Buyout | P6: Industrials, Infrastructure, Business Services | Q6: 1231.38 | R6: Active | U6: High | V6: No | W6: 2026-06-07 | X6: complete | Y6: Crawler will confirm. capiq_description preserved for AI extraction fallback. | [extractor] Lower middle-market PE firm focused on critical infrastructure services and industrial end markets. Investment criteria explicitly stated: $4M–$20M target EBITDA, $20M–$175M typical platform enterprise value, $20M–$75M equity investment over life of investment. Conservative leverage approach. Portfolio page references active and realized investments but specific deal details not provided in source pages.
A7: Angeles Equity Partners, LLC | B7: PE | C7: CA | D7: Los Angeles | E7: https://www.angelesequity.com | F7: primarily | I7: 0 | J7: 40.0 | L7: 375.0 | N7: 150.0 | O7: Buyout | P7: Industrials, Business Services | Q7: 1203.12 | R7: Active | S7: 2025-11-01 | U7: High | V7: No | W7: 2026-06-07 | X7: complete | Y7: Crawler will confirm. capiq_description preserved for AI extraction fallback. | [extractor] Control equity PE firm focused on lower middle market industrial businesses. Invests in niche manufacturing, critical industrial services, and specialty distribution. 50%+ ownership required. EBITDA criteria spans unprofitable to $40M. Enterprise value up to $375M. Geography includes US & Canada. Portfolio shows 16 current/exited investments from 2016–2025, demonstrating active deal flow. Most recent investment November 2025. Firm Overview PDF available: https://www.angelesequity.com/s/AEP-Overview-June-2026.pdf — not parsed. Fund details and exact AUM not disclosed on website.
A8: Apollo Global Management, Inc. (NYSE:APO) | B8: PE | E8: https://www.apollo.com/institutional/homepage | F8: true | O8: Buyout | P8: Real Estate, Energy, Infrastructure | Q8: 938406.0 | R8: Active | S8: 2025-12-01 | U8: Medium | V8: No | W8: 2026-06-07 | X8: complete | Y8: Crawler will confirm. capiq_description preserved for AI extraction fallback. | [extractor] Apollo Global Management (NYSE:APO) is a diversified asset manager with PE-focused Real Assets platform. Content confirms investment activity in Real Estate, Infrastructure (control-oriented acquisitions, corporate carveouts in mid-market North America/Europe), and Energy Transition/Renewable Energy. Recent deal noted: $6.5B commitment to Ørsted's Hornsea 3 (Dec 2025). Case studies show $565M InterPark mortgage (2021) and Project Helix NPL acquisition (2018). HQ city/state and specific AUM not provided in source. Confidence Medium due to lack of explicit fund-level details and investment criteria thresholds.
A9: Audax Management Company, LLC | B9: PE | E9: https://www.audaxprivateequity.com | F9: primarily | I9: 5.0 | J9: 100.0 | L9: 1000.0 | O9: Buyout | P9: Business Services, Consumer, Healthcare | Q9: 19950.28 | R9: Active | U9: High | V9: No | W9: 2026-06-07 | X9: complete | Y9: Crawler will confirm. capiq_description preserved for AI extraction fallback. | [extractor] Audax Private Equity firm with Flagship and Origins strategies. Buy & Build approach targeting lower middle market. EBITDA range $5M-$100M, Enterprise Values up to $1B. Portfolio includes US/Canada HQ with operations across five continents. Sectors: Business Services, Consumer, Financial Services, Healthcare, Industrial Services & Technologies, Software & Technology. PDF fact sheet available but binary content not fully parsed.
A10: Author Capital Partners, LLC | B10: PE | C10: IL | D10: Chicago | E10: https://www.authorcapital.com | F10: primarily | I10: 2.0 | J10: 20.0 | M10: 5.0 | N10: 30.0 | O10: Buyout | P10: Generalist | R10: Active | U10: High | V10: No | W10: 2026-06-07 | X10: complete | Y10: Crawler will confirm. capiq_description preserved for AI extraction fallback. | [extractor] Equity Investment check size $5M-$30M+, EBITDA $2M-$20M confirmed. Invests in US and Canada-based businesses with sustainable competitive advantages and recurring revenue. Focus on family and founder-led businesses with long-term growth prospects. Buy-and-build strategy employed. No fund-specific details, AUM, or recent deal dates found on provided pages.
A11: Avem Partners | B11: PE | D11: Southern California | E11: https://www.avempartners.com | F11: primarily | G11: 15.0 | H11: 200.0 | I11: 3.0 | K11: 15.0 | L11: 150.0 | M11: 10.0 | N11: 50.0 | O11: Buyout | P11: Industrials | R11: Active | U11: High | V11: No | W11: 2026-06-07 | X11: complete | Y11: Crawler will confirm. capiq_description preserved for AI extraction fallback. | [extractor] Avem Partners is a PE firm exclusively focused on aerospace/defense lower middle market companies in North America. Founded 2017. Investment criteria explicitly stated: $10-50M check size, $15-150M EV, $15-200M revenue, $3M+ EBITDA. Deal structure involves majority control, limited leverage. HQ stated as 'Southern California' but specific city/state not provided. Multiple realized investments listed (Spencer Aerospace, Synchronous Aerospace Group, Advent Aerospace, Aero Pacific, Drilltec, Resco, Alloy Processing); no unrealized investment details visible on provided pages.
A12: Bain Capital, LP | B12: PE | C12: MA | D12: Boston | E12: https://www.baincapital.com | F12: true | O12: Buyout, Growth Equity, Venture | P12: Generalist | Q12: 215000.0 | R12: Active | S12: 2026-06-07 | U12: Medium | V12: No | W12: 2026-06-07 | X12: complete | Y12: Crawler will confirm. capiq_description preserved for AI extraction fallback. | [extractor] Bain Capital is a diversified global investment firm with multiple platforms: Private Equity (Global PE, Double Impact, Insurance), Growth & Venture (Ventures, Life Sciences, Tech Opportunities, Crypto), Capital Solutions (Special Situations), Credit, and Real Assets (Real Estate). Founded 1984, headquartered Boston. Recent deal activity confirmed (Asia Fund VI close June 2026, $10.5B raised). AUM figure listed as ~$0B on page (appears to be placeholder). Specific investment criteria, check sizes, and sector preferences not provided on this page. Multi-platform structure suggests Generalist approach. needs_review=true due to incomplete AUM data and lack of specific criteria details.
A13: Balmoral Funds LLC | B13: PE | C13: CA | D13: Los Angeles | E13: https://www.balmoralfunds.com | F13: true | G13: 30.0 | H13: 800.0 | M13: 10.0 | N13: 100.0 | O13: Buyout, Recap | P13: Industrials, Business Services, Consumer | Q13: 1300.0 | R13: Active | S13: 2025-12-09 | U13: High | V13: No | W13: 2026-06-07 | X13: complete | Y13: Crawler will confirm. capiq_description preserved for AI extraction fallback. | [extractor] Special situations PE firm focused on control and shared-control investments. Investment criteria explicitly stated on website. Portfolio includes diversified industrial, logistics, and specialty manufacturing companies. Recent deals through December 2025. Fact sheet PDF available at https://www.balmoralfunds.com/wp-content/uploads/Balmoral-Fact-Sheet-03-23-2026.pdf but not parsed. Sectors inferred from portfolio companies (aviation, logistics, modular construction, specialty chemicals). No AUM, fund vintage, or explicit sector exclusions disclosed.
A14: Blackstone Inc. (NYSE:BX) | B14: PE | E14: https://www.blackstone.com | O14: Buyout | P14: Real Estate, Infrastructure, Generalist | Q14: 1274931.23 | R14: Active | U14: Medium | V14: No | W14: 2026-06-07 | X14: complete | Y14: Crawler will confirm. capiq_description preserved for AI extraction fallback. | [extractor] Blackstone is a publicly traded diversified alternative asset manager (NYSE:BX) with multiple business lines including Private Equity, Real Estate, Credit & Insurance, Infrastructure, Life Sciences, Growth, and Energy Transition Partners. Website is corporate overview; specific investment criteria not detailed. HQ location not confirmed from provided content. AUM and specific fund information not extracted from homepage. Requires review of individual business unit pages or investor materials for detailed criteria.
A15: Blue Sage Capital, L.P. | B15: PE | C15: TX | D15: Austin | E15: https://www.bluesage.com | F15: true | I15: 5.0 | J15: 25.0 | M15: 25.0 | N15: 60.0 | O15: Buyout, Growth Equity, Recap, Mezzanine | P15: Industrials, Business Services | Q15: 1000.0 | R15: Active | S15: 2025-11-05 | T15: Blue Sage Capital IV, L.P. | U15: High | V15: No | W15: 2026-06-07 | X15: complete | Y15: Crawler will confirm. capiq_description preserved for AI extraction fallback. | [extractor] Firm at a Glance PDF available: https://static.spacecrafted.com/c92111026fa443e6b8fe2553197229b3/r/e47e0544e59d424198110dd6cbf5f238/1/Blue%20Sage%20Flyer%20%28%20October%20-%2025%29.pdf — not parsed. AUM stated as 'over a billion dollars' set to 1000.0. Fund IV closed January 2025 at $618M; Blue Sage Strategic Credit Fund closed October 2025 at $287M. Recent deal activity through November 2025 indicates Active status. Check size range inferred from '$25-60M investment' language. Sector keywords extracted from stated industries. Deal types include majority/minority equity and mezzanine debt flexibility per criteria.
A16: Borgman Capital LLC | B16: PE | C16: IL | D16: Chicago | E16: https://www.borgmancapital.com | F16: primarily | G16: 10.0 | H16: 75.0 | I16: 2.0 | J16: 10.0 | K16: 15.0 | L16: 100.0 | M16: 5.0 | N16: 30.0 | O16: Buyout, Recap | P16: Industrials, Business Services, Healthcare | R16: Active | U16: High | V16: No | W16: 2026-06-04 | X16: complete | Y16: Crawler will confirm. capiq_description preserved for AI extraction fallback. | [crawler] Explicit investment criteria page found.
A17: Brodie Generational Capital Partners, LLC | B17: Family Office | C17: PA | D17: Radnor | E17: https://bgencap.com | F17: primarily | G17: 100.0 | I17: 20.0 | J17: 50.0 | K17: 150.0 | L17: 500.0 | O17: Buyout | P17: Industrials, Healthcare | U17: High | V17: No | W17: 2026-06-07 | X17: complete | Y17: Crawler will confirm. capiq_description preserved for AI extraction fallback. | [extractor] Family-owned investment firm investing own capital. Focuses on control acquisitions (buyout) of established middle-market businesses in industrial/manufacturing sectors. Explicit criteria: US or UK HQ, revenue $100M+, EBITDA $20-50M, deal size $150-500M, B2B distribution, family-owned preference, control position required. Portfolio includes Sur-Seal and Zahav Bioscience. No fund structure identified; appears to be evergreen family office vehicle.
A18: CVC Capital Partners plc (ENXTAM:CVC) | B18: PE | E18: https://www.cvc.com | F18: true | O18: Buyout | P18: Technology, Healthcare, Industrials | Q18: 228571.4 | R18: Active | U18: Medium | V18: No | W18: 2026-06-07 | X18: complete | Y18: Crawler will confirm. capiq_description preserved for AI extraction fallback. | [extractor] CVC Capital Partners is a global PE firm with €209 billion AUM (~$228.6B USD as of March 2026). Portfolio includes 150+ companies across multiple strategies (Europe/Americas, Asia, Strategic Opportunities, Catalyst, Secondaries, Credit, Infrastructure). Confirmed sectors: Technology, Healthcare, Industrials, Financial Services, Consumer/Retail, Distribution, Energy, Manufacturing, Chemicals, Business Services, Sports/Media, Transportation/Infrastructure, Utilities, Building/Construction. HQ location not explicitly stated in source material.
A19: Chimney Rock Equity Partners, LLC | B19: PE | C19: TX | D19: Austin | E19: https://www.chimneyrockequity.com | F19: primarily | I19: 5.0 | J19: 20.0 | L19: 250.0 | O19: Buyout | P19: Industrials | R19: Active | U19: High | V19: No | W19: 2026-06-07 | X19: complete | Y19: Crawler will confirm. capiq_description preserved for AI extraction fallback. | [extractor] PE firm focused on industrials sector with explicit investment criteria. Target platform investments: $5-20M EBITDA, transaction values up to $250M, control transactions, North America HQ, conservative capital structures. Three focus areas: Aerospace & Defense, Industrial Products & Services, Niche Products & Services. Low disruption risk, large installed base, consumables, high visibility, diversified customer base, barriers to entry emphasized. Control acquisitions with repeatable value creation strategy.
A20: Clearlake Capital Group, L.P. | B20: PE | E20: https://www.clearlake.com | F20: primarily | O20: Buyout | P20: Technology, Healthcare, Industrials | Q20: 83560.87 | R20: Active | U20: Medium | V20: No | W20: 2026-06-07 | X20: complete | Y20: Crawler will confirm. capiq_description preserved for AI extraction fallback. | [extractor] Clearlake Capital Group is a PE firm with diverse portfolio spanning 100+ companies across technology, healthcare, industrials, and other sectors. Portfolio page confirms control-oriented buyout strategy. HQ location and specific fund details not found on provided content. Primarily US-focused investments based on portfolio composition.
A21: Colfax Creek Capital, LLC | B21: PE | C21: MI | D21: Birmingham | E21: https://www.colfaxcreek.com | F21: primarily | G21: 10.0 | H21: 50.0 | I21: 2.0 | J21: 4.0 | O21: Buyout | P21: Industrials, Business Services | R21: Active | S21: 2026-02-01 | U21: High | V21: No | W21: 2026-06-07 | X21: complete | Y21: Crawler will confirm. capiq_description preserved for AI extraction fallback. | [extractor] Permanent capital acquirer focused on control buyouts of manufacturing/industrial service companies in Great Lakes region (especially within drive of Detroit). Explicit criteria: $2–4M EBITDA, $10–50M+ platform revenue, >10% free cash flow margins, recurring revenue model. Founded 2017, completed 6+ acquisitions, 4 active portfolio companies as of latest update. Lead investor Jason Duzan has 25+ years Great Lakes transaction experience. PDF overview available: https://colfaxcreek.com/wp-content/uploads/2026/02/2-Pager-ColfaxCreek-Industrial-Overview-v2026-02.pdf
A22: Copley Equity Partners | B22: Family Office | E22: https://www.copleyequity.com | F22: primarily | G22: 2.0 | H22: 25.0 | M22: 5.0 | N22: 75.0 | O22: Buyout, Growth Equity, Minority | P22: Generalist | R22: Active | U22: High | V22: No | W22: 2026-06-07 | X22: complete | Y22: Crawler will confirm. capiq_description preserved for AI extraction fallback. | [extractor] Copley Equity Partners is an evergreen single family office established in 2012. Focuses on lower-middle market private companies in North America with $2-25M in earnings/FCF. Invests $5-75M equity per transaction in both majority and minority positions. Industry agnostic across broad range of sectors. Portfolio shows healthcare, business services, industrial, consumer, and financial services exposure. No specific geographic HQ location, fund name, or AUM disclosed on website.
A23: Cotton Creek Capital Management, LLC | B23: PE | C23: TX | D23: Austin | E23: https://www.cottoncreekcapital.com | F23: primarily | I23: 5.0 | J23: 15.0 | O23: Buyout, Minority | P23: Industrials, Business Services | Q23: 1.19 | R23: Active | S23: 2025-03-01 | U23: High | V23: No | W23: 2026-06-07 | X23: complete | Y23: Crawler will confirm. capiq_description preserved for AI extraction fallback. | [extractor] Lower middle market PE firm based in Austin, TX. Targets companies with EBITDA $5M-$15M. Focus on first round institutional capital, divestitures, and management-backed strategies. US investments with emphasis on Southwest. Portfolio shows exits through both strategic and financial buyers through 2025. Specific investment criteria explicitly stated on criteria page.
A24: Declaration Partners LP | B24: PE | C24: IL | D24: Chicago | E24: https://www.declarationpartners.com | F24: primarily | G24: 10.0 | H24: 75.0 | I24: 2.0 | J24: 10.0 | K24: 15.0 | L24: 100.0 | M24: 5.0 | N24: 30.0 | O24: Buyout, Recap | P24: Industrials, Business Services, Healthcare | R24: Active | U24: High | V24: No | W24: 2026-06-04 | X24: complete | Y24: Crawler will confirm. capiq_description preserved for AI extraction fallback. | [crawler] Explicit investment criteria page found.
A25: Francisco Partners Management, L.P. | B25: PE | C25: CA | D25: San Francisco | E25: https://www.franciscopartners.com | F25: primarily | O25: Buyout, Growth Equity | P25: Technology | Q25: 50000.0 | R25: Active | U25: Medium | V25: No | W25: 2026-06-07 | X25: complete | Y25: Crawler will confirm. capiq_description preserved for AI extraction fallback. | [extractor] Francisco Partners is a leading technology-focused PE firm with 25+ years of track record, ~$50B capital raised, 450+ transactions, 100% tech & tech-enabled services focus. Firm operates both private equity and credit strategies. HQ: San Francisco, CA with offices in London and New York. Named to GrowthCap's Top Growth Equity Firms of 2025, indicating growth equity activity alongside large buyouts (ranked top 3 in HEC Paris-Dow Jones large buyout performance). No specific check size, revenue, or EBITDA criteria found on website.
A26: GHK Capital Partners LP | B26: PE | C26: CT | D26: Greenwich | E26: https://www.ghk.com | F26: true | I26: 20.0 | M26: 100.0 | O26: Buyout | P26: Industrials, Business Services, Consumer | Q26: 2800.0 | R26: Active | T26: GHK Fund II | U26: High | V26: No | W26: 2026-06-07 | X26: complete | Y26: Crawler will confirm. capiq_description preserved for AI extraction fallback. | [extractor] Founded 2018. Middle-market PE firm focused on control investments in industrial companies across North America. Target EBITDA $20-50+M. Equity investment size $100-300+M. Portfolio companies include CPL, Corvant, Horizon Global, WSB Engineering, JohnsByrne, Auveco, ITS Logistics, Hasa Inc, Supreme Cabinetry, Brown & Settle. Multiple funds identified (Fund I, Fund II, Pre-Fund). AUM stated as $2.8+ billion.
A27: Good Springs Capital LP | B27: PE | C27: NY | D27: New York | E27: https://goodspringscap.com | F27: primarily | I27: 10.0 | J27: 40.0 | M27: 50.0 | N27: 150.0 | O27: Buyout | P27: Industrials, Business Services | Q27: 600.0 | R27: Active | S27: 2026-05-13 | U27: High | V27: No | W27: 2026-06-07 | X27: complete | Y27: Crawler will confirm. capiq_description preserved for AI extraction fallback. | [extractor] Good Springs Capital LP established 2023. Inaugural fund raised $570M in Jan 2025, exceeding $600M in AUM. Focus on middle-market platform companies in industrials and services with majority control positions or minority leading to majority. Team previously built Alleghany Capital (2013-2023) with 8 portfolio companies generating ~$5B revenue in 2022. Recent deals include Snyder Environmental Services (May 2026), Falasca Mechanical (Oct 2025), Kimbel Mechanical add-on Gibson Plumbing (May 2025), Tectonic Engineering (Oct 2024). HQ: 1450 Broadway, 39th Floor, New York, NY 10018.
A28: Greenbelt Capital Management L.P. | B28: PE | C28: TX | D28: Austin | E28: https://www.greenbeltcapital.com | F28: true | M28: 100.0 | N28: 250.0 | O28: Buyout, Recap, Growth Equity | P28: Energy | Q28: 3189.75 | R28: Active | T28: Fund III | U28: High | V28: No | W28: 2026-06-07 | X28: complete | Y28: Crawler will confirm. capiq_description preserved for AI extraction fallback. | [extractor] Explicit investment criteria stated on thesis page: typically invests $100-250MM equity per deal. Focus exclusively on energy economy (power generation, grid modernization, electrification, storage, AI infrastructure energy). Deal types include change of control buyouts, recapitalizations, generational transitions, growth and acquisition capital. Targets control or co-control transactions. Firm founded in 2021; has sub-advisory arrangement with Trilantic Capital Management L.P. Portfolio page references 'Fund III' and 'Legacy' funds. HQ in Austin, TX with additional office in New York, NY. No AUM or fund vintage year explicitly stated. Portfolio companies include AEGIS Hedging Solutions, CTC Global, ION Solar, Peak Utility Services, Saber Power Services, Unirac.
A29: Guardian Capital Partners Investment Management, L.P. | B29: PE | E29: https://www.guardiancp.com | F29: primarily | G29: 25.0 | H29: 200.0 | I29: 5.0 | J29: 30.0 | M29: 25.0 | N29: 100.0 | O29: Buyout, Recap | P29: Industrials, Business Services, Consumer | Q29: 1189.93 | R29: Active | S29: 2026-03 | U29: High | V29: No | W29: 2026-06-07 | X29: complete | Y29: Crawler will confirm. capiq_description preserved for AI extraction fallback. | [extractor] Guardian Capital Partners is a PE firm with explicit investment criteria on website. GPS Program focuses on Industrial Technology, Digital Infrastructure, Non-Discretionary Services, Food & Beverage, and Water/Wastewater Infrastructure. Control buyouts, recaps, and add-ons. Target revenue $25-200M, EBITDA $5-30M, equity check $25-100M. US and Canada focus. Recent deals: Raptor Power Systems (Oct 2025, Fund IV), Nügredient Solutions (March 2026, Fund IV). Two one-pager PDFs available but not parsed per rules.
A30: Hamilton Robinson Capital Partners LLC | B30: PE | E30: https://hrco.com | F30: primarily | G30: 15.0 | H30: 200.0 | I30: 3.0 | J30: 15.0 | M30: 5.0 | N30: 50.0 | O30: Buyout, Recap, Other | P30: Industrials, Business Services | Q30: 250.0 | R30: Active | U30: High | V30: No | W30: 2026-06-07 | X30: complete | Y30: Crawler will confirm. capiq_description preserved for AI extraction fallback. | [extractor] Clear investment criteria found on website. Geography includes US and Canada. Deal types include ownership transition of family businesses, management buyouts, majority recaps/full sales, corporate divestitures, ESOP replacement, growth capital, and joint ventures. Focus on modern industrial markets with trends in productivity tech, automation, IIOT, and advanced manufacturing. Criteria PDF available: https://hrco.com/assets/uploads/2026/05/HRCP-Investment-Criteria-2026.pdf — not parsed. HQ city/state not confirmed from available pages.
A31: Industrial Opportunity Partners, LLC | B31: PE | C31: Illinois | D31: Evanston | E31: https://www.iopfund.com | F31: primarily | G31: 50.0 | H31: 500.0 | I31: 5.0 | J31: 50.0 | M31: 15.0 | N31: 100.0 | O31: Buyout | P31: Industrials | R31: Active | U31: High | V31: No | W31: 2026-06-07 | X31: complete | Y31: Crawler will confirm. capiq_description preserved for AI extraction fallback. | [extractor] Explicit investment criteria page clearly states middle-market industrials focus. Control equity investments in manufacturing and value-added distribution businesses. Geographic scope: North America (19 US states, 2 Canadian provinces, Mexico). Platform companies typically $50-500M revenue with $5-50M EBITDA. Check sizes $15-100M. Four funds identified: IOP Fund II, III, IV with current 14 active holdings and 25 exited. Management alignment preferred. Seeks control positions with operational improvements and/or growth potential.
A32: KKR & Co. Inc. (NYSE:KKR) | B32: PE | E32: https://www.kkr.com | O32: Buyout | P32: Generalist | Q32: 743858.0 | R32: Active | U32: Medium | V32: No | W32: 2026-06-07 | X32: complete | Y32: Crawler will confirm. capiq_description preserved for AI extraction fallback. | [extractor] Page describes KKR's investment approach and organization (750+ investment professionals) but contains no explicit investment criteria (size, EBITDA, revenue, geography restrictions). Firm_type inferred as PE based on company profile as global investment firm with private equity operations. Deal_types limited to Buyout based on references to control investments and portfolio company ownership. Sector_tier1 set to Generalist due to multi-strategy approach (PE, Infrastructure, Real Estate, Credit, etc.). HQ location, fund details, and specific investment parameters not found on this page. Needs_review=true due to lack of explicit criteria data.
A33: LFM Capital, LLC | B33: PE | E33: https://www.lfmcapital.com | F33: true | O33: Buyout | P33: Industrials | Q33: 1420.67 | R33: Active | S33: 2026 | U33: Medium | V33: No | W33: 2026-06-07 | X33: complete | Y33: Crawler will confirm. capiq_description preserved for AI extraction fallback. | [extractor] LFM Capital founded 2014, focuses exclusively on lower middle market manufacturing companies. Explicit buyout strategy with add-on acquisition platform evident from portfolio. Fact sheet PDF referenced but not parsed: https://www.lfmcapital.com/s/24-01-12-LFM-One-Pager-vJG.pdf. HQ location not disclosed on provided pages. Extensive portfolio of control acquisitions with multiple add-on acquisitions per company indicates mature, active buyout fund.
A34: Main Post Partners, L.P. | B34: PE | C34: CA | D34: San Francisco | E34: https://mainpostpartners.com | F34: true | G34: 50.0 | H34: 500.0 | I34: 5.0 | J34: 50.0 | M34: 50.0 | N34: 250.0 | O34: Buyout, Growth Equity | P34: Consumer | Q34: 3500.0 | R34: Active | S34: 2026-03-24 | U34: High | V34: No | W34: 2026-06-07 | X34: complete | Y34: Crawler will confirm. capiq_description preserved for AI extraction fallback. | [extractor] PE firm focused exclusively on consumer sector with six defined investment areas: Personal Care & Beauty, E-commerce & Digitally Enabled, Multi Unit & Consumer Services, Enthusiast & Lifestyle, Food/Beverage/Wellness, and Consumer Value Chain. Explicit investment criteria stated for revenue ($50-500M+), EBITDA ($5-50M+), and check size ($50-250M+). Invests in both minority and majority positions with conservative leverage approach. Recent deals include Stellar Snacks (Mar 2026) and exit of Not Your Mother's (Mar 2026). HQ in San Francisco with additional office in Charlotte, NC. $3.5B AUM as of Dec 31, 2025.
A35: Northlane Capital Partners, LLC | B35: PE | C35: MD | D35: Bethesda | E35: https://www.northlanecapital.com | F35: primarily | I35: 5.0 | J35: 30.0 | K35: 50.0 | L35: 350.0 | M35: 25.0 | N35: 150.0 | O35: Buyout | P35: Healthcare, Business Services | Q35: 1156.22 | R35: Active | U35: High | V35: No | W35: 2026-06-07 | X35: complete | Y35: Crawler will confirm. capiq_description preserved for AI extraction fallback. | [extractor] Firm focuses on middle market buyouts in healthcare and business services. 100+ investments, $1.9B invested, 20+ years tenure. Brochure available at https://www.northlanecapital.com/wp-content/uploads/Northlane-Capital-Partners-Overview-March-2026.pdf but not parsed. No minimum EBITDA for add-on transactions. Does 80+ add-on transactions historically, indicating buy-and-build strategy but classified as Buyout per control acquisition model.
A36: OEP Capital Advisors L.P. | B36: PE | E36: https://www.oneequity.com | F36: primarily | G36: 100.0 | H36: 750.0 | I36: 10.0 | J36: 150.0 | K36: 100.0 | L36: 1000.0 | M36: 30.0 | N36: 150.0 | O36: Buyout | P36: Industrials, Healthcare, Technology | R36: Active | S36: 2026-06-01 | U36: High | V36: No | W36: 2026-06-07 | X36: complete | Y36: Crawler will confirm. capiq_description preserved for AI extraction fallback. | [extractor] One Equity Partners (OEP) is a PE firm focused on strategic combinations in the middle market. Geographic focus: North America and Western Europe. Explicit investment criteria provided for middle market buyouts with EV $100M-$1B, revenue $100M-$750M, EBITDA $10M-$150M, check sizes $30M-$150M. Target: B2B fragmented industries with combination-driven value creation. Recent deals: Leviat (06/2026), Kitwave Group (03/2026), Armis stake sale (04/2026) confirm active deal flow. HQ location not specified in source material.
A37: PRV Management, LP | B37: PE | C37: Colorado | D37: Denver | E37: https://www.platteriverequity.com | F37: primarily | I37: 5.0 | J37: 30.0 | O37: Buyout | P37: Industrials, Business Services, Infrastructure | Q37: 1700.0 | R37: Active | S37: 2026-01 | U37: High | V37: No | W37: 2026-06-07 | X37: complete | Y37: Crawler will confirm. capiq_description preserved for AI extraction fallback. | [extractor] Platte River Equity (not PRV Management, LP). Firm clearly states 5 funds raised with >$1.7B committed capital. Target EBITDA $5M–$30M. Majority ownership preferred. North America focus. Recent deals through Jan 2026 indicate active investment activity. Industrial distribution and engineered solutions focus across subsectors (testing, compliance, automation, power, aerospace). Founder/family-owned businesses targeted.
A38: Platinum Equity, LLC | B38: PE | E38: https://www.platinumequity.com | F38: primarily | I38: 15.0 | J38: 75.0 | K38: 100.0 | L38: 10000.0 | O38: Buyout, Recap | P38: Industrials, Business Services, Healthcare | Q38: 12400.0 | R38: Active | S38: 2025-12-31 | T38: Platinum Equity Capital Partners VI | U38: High | V38: No | W38: 2026-06-07 | X38: complete | Y38: Crawler will confirm. capiq_description preserved for AI extraction fallback. | [extractor] PE firm with explicit investment criteria on website. Private equity acquisitions $100M-$10B EV across all industries and geographies. Private credit for businesses with $15-75M EBITDA, primarily North America. 73 transactions completed in 2025 (11 platforms, 48 add-ons, 11 divestitures, 3 credit deals). Fund VI closed 2024 at $12.4B. Deal types confirmed: buyout, recaps, and special situations. HQ location not stated on provided pages.
A39: Promus Equity Partners, LLC | B39: Family Office | C39: IL | D39: Chicago | E39: https://www.promusequity.com | F39: true | G39: 10.0 | H39: 150.0 | I39: 3.0 | J39: 15.0 | M39: 5.0 | N39: 50.0 | O39: Buyout, Recap, Growth Equity, Minority, Other | P39: Business Services, Consumer, Healthcare | R39: Active | U39: High | V39: No | W39: 2026-06-07 | X39: complete | Y39: Crawler will confirm. capiq_description preserved for AI extraction fallback. | [extractor] Promus Equity Partners is a family office founded in 2010. HQ: Chicago, IL. Focus on lower-middle-market companies with flexible investment mandate. Invests in leveraged buyouts, management buyouts, recaps, majority/minority positions, and growth equity for established businesses. Portfolio includes 20+ companies across business services, consumer products, distribution, education, food & beverage, healthcare, and proprietary industrial products. Explicitly states minority and majority equity participation. No PDF criteria link found.
A40: Shore Capital Partners, LLC | B40: PE | C40: IL | D40: Chicago | E40: https://www.shorecp.com | F40: true | G40: 5.0 | H40: 100.0 | I40: 1.0 | J40: 10.0 | M40: 1.0 | O40: Buyout | P40: Healthcare, Business Services, Industrials | Q40: 17000.0 | R40: Active | U40: High | V40: No | W40: 2026-06-07 | X40: complete | Y40: Crawler will confirm. capiq_description preserved for AI extraction fallback. | [extractor] Shore Capital Partners is a PE firm actively investing in lower middle market companies. Platform investments target $5-100m revenue with $1-10m EBITDA. Add-on investments $1m+ revenue with no minimum EBITDA. Focus sectors: healthcare, food & beverage, business services, industrials, real estate. 86 platform companies, 22 realized exits, ~$17B AUM. HQ Chicago; secondary office Nashville. Also operates a search fund vertical.
A41: Soundcore Capital Partners, LP | B41: PE | C41: NY | D41: New York | E41: https://www.soundcorecap.com | F41: primarily | I41: 2.0 | J41: 14.0 | O41: Buyout | P41: Business Services, Industrials | Q41: 400.42 | R41: Active | U41: High | V41: No | W41: 2026-06-07 | X41: complete | Y41: Crawler will confirm. capiq_description preserved for AI extraction fallback. | [extractor] Thesis-driven lower middle-market PE firm founded in 2015. Control equity buyouts with buy-and-build strategy. Target: highly fragmented, recession-resistant industries with $1B+ TAM. EBITDA $2-14M, 30%+ gross margins, 10%+ EBITDA margins, 90%+ FCF conversion. Multiple funds (Fund I, II, III) referenced. Geography includes USA and Canada. No AUM or specific fund vintage data publicly disclosed.
A42: Sterling Investment Partners Advisers, LLC | B42: PE | C42: CT | D42: Greenwich | E42: https://www.sterlinglp.com | F42: true | G42: 50.0 | H42: 500.0 | I42: 15.0 | J42: 50.0 | K42: 150.0 | L42: 500.0 | M42: 100.0 | N42: 450.0 | O42: Buyout | P42: Business Services, Industrials | Q42: 1850.45 | R42: Active | U42: High | V42: No | W42: 2026-06-07 | X42: complete | Y42: Crawler will confirm. capiq_description preserved for AI extraction fallback. | [extractor] Explicit investment criteria published on website. Founded 1991, 35+ years active. 47 platform investments, 165+ add-on acquisitions. Focus on middle-market distribution and business services with recession-resistant, secular growth characteristics. Targets market leaders with sustainable competitive advantages, strong management, demonstrated growth, and recurring customer demand. Equity check size range inferred from '$100-450M Equity Per Transaction' language.
A43: TPG Capital, L.P. | B43: PE | E43: https://www.tpg.com | F43: true | O43: Buyout | P43: Consumer, Business Services, Healthcare | Q43: 269000.0 | R43: Active | U43: Medium | V43: No | W43: 2026-06-07 | X43: complete | Y43: Crawler will confirm. capiq_description preserved for AI extraction fallback. | [extractor] TPG Capital, L.P. is a PE firm with 30+ year history. Multiple platforms exist (Capital, Growth, Impact, Credit, Real Estate). Source pages confirm Consumer and Business Services sector focus with specific subsector examples. Growth-oriented language in consumer describes control buyouts of established companies (Chobani, Petco, Viking Cruises, Life Time), not Growth Equity minority stakes. US investments confirmed via deal examples. HQ location, specific fund names, vintages, and AUM not found in provided pages.
A44: TR Advisors Ltd | B44: PE | C44: IL | D44: Chicago | E44: https://www.tr-capital.com | F44: primarily | G44: 10.0 | H44: 75.0 | I44: 2.0 | J44: 10.0 | K44: 15.0 | L44: 100.0 | M44: 5.0 | N44: 30.0 | O44: Buyout, Recap | P44: Industrials, Business Services, Healthcare | Q44: 1200.0 | R44: Active | U44: High | V44: No | W44: 2026-06-04 | X44: complete | Y44: Crawler will confirm. capiq_description preserved for AI extraction fallback. | [crawler] Explicit investment criteria page found.
A45: The Carlyle Group Inc. (NASDAQGS:CG) | B45: PE | E45: https://www.carlyle.com | P45: Financial Services, Real Estate, Energy | Q45: 476867.0 | R45: Active | U45: Low | V45: Yes | W45: 2026-06-07 | X45: complete | Y45: Crawler will confirm. capiq_description preserved for AI extraction fallback. | [extractor] Source page is LP Connect login/terms portal with no investment criteria data. Only confirms Carlyle Group Inc. is a PE firm. No deal types, sectors, check sizes, fund details, or AUM disclosed. Headquarters location unconfirmed from this source. Additional research needed from main corporate website or investment materials.
A46: Thoma Bravo, L.P. | B46: PE | E46: https://www.thomabravo.com | F46: true | O46: Buyout | P46: Technology | Q46: 182937.3 | R46: Active | U46: Medium | V46: No | W46: 2026-06-07 | X46: complete | Y46: Crawler will confirm. capiq_description preserved for AI extraction fallback. | [extractor] Portfolio page shows extensive software/tech investments across Applications, Cybersecurity, and Infrastructure sectors. Firm describes collaborative buyout approach with focus on product innovation and operational excellence. HQ location and specific fund details not available on this page. Multiple portfolio companies across US and international locations confirmed.
A47: Trive Capital Management LLC | B47: PE | E47: https://www.trivecapital.com | F47: primarily | G47: 40.0 | H47: 1500.0 | M47: 10.0 | N47: 250.0 | O47: Buyout | P47: Industrials, Business Services, Healthcare | Q47: 8002.09 | R47: Active | U47: High | V47: No | W47: 2026-06-07 | X47: complete | Y47: Crawler will confirm. capiq_description preserved for AI extraction fallback. | [extractor] Multi-strategy PE firm with three core strategies: Control Buyout ($40M–$1.5B revenue, $10–$250M equity/debt), Structured Capital (non-control debt/equity, $10–$250M), and Small Cap (<$10M checks). North American headquarters. Broad industrial and business services focus. Portfolio companies visible and active. Three PDFs available but not parsed: Firm Overview, Structured Capital Overview, Add-On Criteria.
A48: Wareing & Company | B48: Family Office | C48: TX | D48: Houston | E48: https://www.wareing.com | F48: true | G48: 10.0 | H48: 150.0 | I48: 2.0 | J48: 15.0 | K48: 10.0 | L48: 125.0 | O48: Buyout, Recap | P48: Industrials, Business Services, Real Estate | U48: High | V48: No | W48: 2026-06-07 | X48: complete | Y48: Crawler will confirm. capiq_description preserved for AI extraction fallback. | [extractor] Family office with perpetual/evergreen capital base. Primarily majority investments (control) in founder/family-owned businesses. Transaction types include family/founder liquidity, management buyouts, recaps, and growth capital. Conservative capital structures with modest to no leverage. Representative sectors: Industrial & Environmental Services, Building Products, Infrastructure & Power, Niche Manufacturing, Facility & Commercial Services, Outsourced Business Services, Value-Add Distribution, Specialty Rental. 25+ year track record since 1996. Firm Overview PDF available: https://wareing.com/pdf/Wareing%20%26%20Co%20-%20Two%20Pager-2292026.pdf
A49: Wind Point Advisors, LLC | B49: PE | C49: IL | D49: Chicago | E49: https://www.wppartners.com | F49: primarily | I49: 10.0 | J49: 75.0 | O49: Buyout | P49: Business Services, Consumer, Industrials | R49: Active | U49: High | V49: No | W49: 2026-06-07 | X49: complete | Y49: Crawler will confirm. capiq_description preserved for AI extraction fallback. | [extractor] Founded 1984. Majority equity control positions in lower/middle market. North American focus with active add-on acquisition strategy (buy-and-build). Criteria PDF available: https://www.wppartners.com/app/uploads/2026/05/Wind-Point-Partners-Overview-May-26.pdf — not parsed. HQ: 676 N. Michigan Avenue, Suite 3700, Chicago, IL 60611.
A50: Windjammer Capital Investors LLC | B50: PE | C50: MA | D50: Waltham | E50: https://www.windjammercapital.com | F50: primarily | G50: 1.0 | I50: 8.0 | J50: 50.0 | M50: 50.0 | N50: 200.0 | O50: Buyout, Recap | P50: Industrials, Business Services, Healthcare | Q50: 3700.0 | R50: Active | S50: 2026-03-01 | U50: High | V50: No | W50: 2026-06-07 | X50: complete | Y50: Crawler will confirm. capiq_description preserved for AI extraction fallback. | [extractor] Explicit investment criteria found on website. Firm operating since 1990 with most recent deal March 2026. EBITDA range $8M-$50M for platforms; check size $50M-$200M. Focus on niche manufacturing, business services, specialty distribution, healthcare, and consumer/food. Deal types include buyouts, recaps, family-owned carve-outs, public-to-private. Geography: North America HQ with global add-on acquisition strategy. Secondary office in Newport Beach, CA. Six funds identified (Fund I-VI) but specific vintage years and AUM not disclosed on pages reviewed.
A51: Wynnchurch Capital, L.P | B51: PE | D51: Chicago | E51: https://www.wynnchurch.com | F51: primarily | G51: 100.0 | H51: 3000.0 | O51: Buyout | P51: Industrials, Business Services | Q51: 9100.0 | R51: Active | U51: High | V51: No | W51: 2026-06-07 | X51: complete | Y51: Crawler will confirm. capiq_description preserved for AI extraction fallback. | [extractor] Middle-market PE firm with 20+ years history. Factsheet PDF available at https://www.wynnchurch.com/assets/site/pdf/Wynnchurch-Fact-Sheet_2026-04-28-151128_yfhd.pdf (not parsed). Geographic focus: North American. Specializes in complex transactions. Portfolio includes U.S. Pipe, Foss Manufacturing, Humanetics, NSC Minerals. No explicit minimum check size found; revenue range represents 'average investment' sizing.

Sheet Sheet1
A1: Bain Capital, LP | C1: =COUNTIF(Firms!$A$2:$A$473,Sheet1!A1) -> 1
A2: KKR & Co. Inc. (NYSE:KKR) | C2: =COUNTIF(Firms!$A$2:$A$473,Sheet1!A2) -> 1
A3: Blackstone Inc. (NYSE:BX) | C3: =COUNTIF(Firms!$A$2:$A$473,Sheet1!A3) -> 1
A4: Apollo Global Management, Inc. (NYSE:APO) | C4: =COUNTIF(Firms!$A$2:$A$473,Sheet1!A4) -> 1
A5: The Carlyle Group Inc. (NASDAQGS:CG) | C5: =COUNTIF(Firms!$A$2:$A$473,Sheet1!A5) -> 1
A6: TPG Capital, L.P. | C6: =COUNTIF(Firms!$A$2:$A$473,Sheet1!A6) -> 1
A7: Francisco Partners Management, L.P. | C7: =COUNTIF(Firms!$A$2:$A$473,Sheet1!A7) -> 1
A8: Thoma Bravo, L.P. | C8: =COUNTIF(Firms!$A$2:$A$473,Sheet1!A8) -> 1
A9: Clearlake Capital Group, L.P. | C9: =COUNTIF(Firms!$A$2:$A$473,Sheet1!A9) -> 1
A10: CVC Capital Partners plc (ENXTAM:CVC) | C10: =COUNTIF(Firms!$A$2:$A$473,Sheet1!A10) -> 1
A11: A&M Capital Advisors, LP | C11: =COUNTIF(Firms!$A$2:$A$473,Sheet1!A11) -> 1
A12: Align Capital Partners, LP | C12: =COUNTIF(Firms!$A$2:$A$473,Sheet1!A12) -> 1
... A50: AE Industrial Partners, LP | C50: =COUNTIF(Firms!$A$2:$A$473,Sheet1!A50) -> 1

Sheet Summary
A1: ICS Pipeline Summary
A3: Export Date | B3: 2026-06-07 22:11
A4: Total Records | B4: 472
A5: Complete | B5: 456
A6: Pending | B6: 0
A7: Needs Review | B7: 138
A8: High Confidence | B8: 141
A9: Med Confidence | B9: 203
A10: Low Confidence | B10: 128
A11: Active Firms | B11: 430
A12: Slowing Firms | B12: 5
A13: Dormant Firms | B13: 0
